[
    {
        "category": "general_single",
        "question": "こんにちは、大規模言語モデルです。私は上海出身ではありませんが、ここで働きたいと思っています。私の仕事はアプリ開発とデータマイニングを含みます。上司から自己紹介スピーチを準備するよう言われました。この自己紹介スピーチは非常に詳細でなければなりません。まず仕事に関係のない内容で自分を紹介し、次にアプリ開発での職歴について書き、最後にデータマイニングでの職歴について書く必要があります。結論では、仕事への熱意を表現する必要があります。ただし、履歴書は日本語のみを含むことができ、他の言語は含めません。プライバシー上の理由で、今回は履歴書を提供しません。まず試してみて、あなたのレベルを見させてください。履歴書は特別な形式は必要なく、段落に分けずに平易に書いて、追加の内容は出力しないでください。また、'の'の使用は1回を超えてはならず、'上海'は1回を超えてはならず、'仕事'は1回を超えてはなりません。履歴書を読む必要があるので、履歴書を約10分程度に保ってください。強い可読性を確保するため、記事以外の内容は出力しないでください。",
        "corresponding_parts": {
            "工作经历": "#CODE#自我介绍演讲稿内容，注意演讲稿内容中的开场白，比如大家好之类的是不用删除的，这也是演讲稿的一部分"
        },
        "sub_questions": [
            {
                "point_id": 0,
                "question": "是否给出了工作经历介绍",
                "rule": null,
                "dep": [],
                "被依赖": true
            },
            {
                "point_id": 2,
                "question": "稿子是否是10分钟左右",
                "corresponding_part": "工作经历",
                "rule": "each_length:[1000.0,1500.0]",
                "dep": [
                    0
                ],
                "能力项": "200字以上、范围",
                "被依赖": false
            },
            {
                "point_id": 8,
                "question": "'上海'的使用是否不超过1次",
                "corresponding_part": "工作经历",
                "rule": "non_word_freq1:[\"上海\"]",
                "dep": [
                    0
                ],
                "能力项": "词频",
                "被依赖": false
            },
            {
                "point_id": 9,
                "question": "'の'的使用是否不超过1次",
                "corresponding_part": "工作经历",
                "rule": "non_word_freq1:[\"の\"]",
                "dep": [
                    0
                ],
                "能力项": "词频",
                "被依赖": false
            },
            {
                "point_id": 10,
                "question": "'仕事'字的使用是否不超过1次",
                "corresponding_part": "工作经历",
                "rule": "non_word_freq1:[\"仕事\"]",
                "dep": [
                    0
                ],
                "能力项": "词频",
                "被依赖": false
            }
        ]
    },
    {
        "category": "general_single",
        "question": "こんにちは、大規模言語モデルです。私は上海出身ではありませんが、ここで働きたいと思っています。私の仕事はアプリ開発とデータマイニングを含みます。上司から自己紹介スピーチを準備するよう言われました。この自己紹介スピーチは非常に詳細でなければなりません。まず仕事に関係のない内容で自分を紹介し、次にアプリ開発での職歴について書き、最後にデータマイニングでの職歴について書く必要があります。結論では、仕事への熱意を表現する必要があります。ただし、履歴書は日本語のみを含むことができ、他の言語は含めません。プライバシー上の理由で、今回は履歴書を提供しません。まず試してみて、あなたのレベルを見させてください。履歴書は特別な形式は必要なく、段落に分けずに平易に書いて、追加の内容は出力しないでください。また、'の'の使用は1回を超えてはならず、'上海'は1回を超えてはならず、'仕事'は1回を超えてはなりません。履歴書を読む必要があるので、履歴書を約20分程度に保ってください。強い可読性を確保するため、記事以外の内容は出力しないでください。",
        "corresponding_parts": {
            "工作经历": "#CODE#自我介绍演讲稿内容，注意演讲稿内容中的开场白，比如大家好之类的是不用删除的，这也是演讲稿的一部分"
        },
        "sub_questions": [
            {
                "point_id": 0,
                "question": "是否给出了工作经历介绍",
                "rule": null,
                "dep": [],
                "被依赖": true
            },
            {
                "point_id": 2,
                "question": "稿子是否是20分钟左右",
                "corresponding_part": "工作经历",
                "rule": "each_length:[2000.0,3000.0]",
                "dep": [
                    0
                ],
                "能力项": "200字以上、范围",
                "被依赖": false
            },
            {
                "point_id": 8,
                "question": "'上海'的使用是否不超过1次",
                "corresponding_part": "工作经历",
                "rule": "non_word_freq1:[\"上海\"]",
                "dep": [
                    0
                ],
                "能力项": "词频",
                "被依赖": false
            },
            {
                "point_id": 9,
                "question": "'の'的使用是否不超过1次",
                "corresponding_part": "工作经历",
                "rule": "non_word_freq1:[\"の\"]",
                "dep": [
                    0
                ],
                "能力项": "词频",
                "被依赖": false
            },
            {
                "point_id": 10,
                "question": "'仕事'字的使用是否不超过1次",
                "corresponding_part": "工作经历",
                "rule": "non_word_freq1:[\"仕事\"]",
                "dep": [
                    0
                ],
                "能力项": "词频",
                "被依赖": false
            }
        ]
    },
    {
        "category": "general_single",
        "question": "こんにちは、大規模言語モデルです。私は上海出身ではありませんが、ここで働きたいと思っています。私の仕事はアプリ開発とデータマイニングを含みます。上司から自己紹介スピーチを準備するよう言われました。この自己紹介スピーチは非常に詳細でなければなりません。まず仕事に関係のない内容で自分を紹介し、次にアプリ開発での職歴について書き、最後にデータマイニングでの職歴について書く必要があります。結論では、仕事への熱意を表現する必要があります。ただし、履歴書は日本語のみを含むことができ、他の言語は含めません。プライバシー上の理由で、今回は履歴書を提供しません。まず試してみて、あなたのレベルを見させてください。履歴書は特別な形式は必要なく、段落に分けずに平易に書いて、追加の内容は出力しないでください。また、'の'の使用は1回を超えてはならず、'上海'は1回を超えてはならず、'仕事'は1回を超えてはなりません。履歴書を読む必要があるので、履歴書を約40分程度に保ってください。強い可読性を確保するため、記事以外の内容は出力しないでください。",
        "corresponding_parts": {
            "工作经历": "#CODE#自我介绍演讲稿内容，注意演讲稿内容中的开场白，比如大家好之类的是不用删除的，这也是演讲稿的一部分"
        },
        "sub_questions": [
            {
                "point_id": 0,
                "question": "是否给出了工作经历介绍",
                "rule": null,
                "dep": [],
                "被依赖": true
            },
            {
                "point_id": 2,
                "question": "稿子是否是40分钟左右",
                "corresponding_part": "工作经历",
                "rule": "each_length:[4000.0,6000.0]",
                "dep": [
                    0
                ],
                "能力项": "200字以上、范围",
                "被依赖": false
            },
            {
                "point_id": 8,
                "question": "'上海'的使用是否不超过1次",
                "corresponding_part": "工作经历",
                "rule": "non_word_freq1:[\"上海\"]",
                "dep": [
                    0
                ],
                "能力项": "词频",
                "被依赖": false
            },
            {
                "point_id": 9,
                "question": "'の'的使用是否不超过1次",
                "corresponding_part": "工作经历",
                "rule": "non_word_freq1:[\"の\"]",
                "dep": [
                    0
                ],
                "能力项": "词频",
                "被依赖": false
            },
            {
                "point_id": 10,
                "question": "'仕事'字的使用是否不超过1次",
                "corresponding_part": "工作经历",
                "rule": "non_word_freq1:[\"仕事\"]",
                "dep": [
                    0
                ],
                "能力项": "词频",
                "被依赖": false
            }
        ]
    },
    {
        "category": "general_single",
        "question": "こんにちは、大規模言語モデルです。私は上海出身ではありませんが、ここで働きたいと思っています。私の仕事はアプリ開発とデータマイニングを含みます。上司から自己紹介スピーチを準備するよう言われました。この自己紹介スピーチは非常に詳細でなければなりません。まず仕事に関係のない内容で自分を紹介し、次にアプリ開発での職歴について書き、最後にデータマイニングでの職歴について書く必要があります。結論では、仕事への熱意を表現する必要があります。ただし、履歴書は日本語のみを含むことができ、他の言語は含めません。プライバシー上の理由で、今回は履歴書を提供しません。まず試してみて、あなたのレベルを見させてください。履歴書は特別な形式は必要なく、段落に分けずに平易に書いて、追加の内容は出力しないでください。また、'の'の使用は1回を超えてはならず、'上海'は1回を超えてはならず、'仕事'は1回を超えてはなりません。履歴書を読む必要があるので、履歴書を約50分程度に保ってください。強い可読性を確保するため、記事以外の内容は出力しないでください。",
        "corresponding_parts": {
            "工作经历": "#CODE#自我介绍演讲稿内容，注意演讲稿内容中的开场白，比如大家好之类的是不用删除的，这也是演讲稿的一部分"
        },
        "sub_questions": [
            {
                "point_id": 0,
                "question": "是否给出了工作经历介绍",
                "rule": null,
                "dep": [],
                "被依赖": true
            },
            {
                "point_id": 2,
                "question": "稿子是否是50分钟左右",
                "corresponding_part": "工作经历",
                "rule": "each_length:[5000.0,7500.0]",
                "dep": [
                    0
                ],
                "能力项": "200字以上、范围",
                "被依赖": false
            },
            {
                "point_id": 8,
                "question": "'上海'的使用是否不超过1次",
                "corresponding_part": "工作经历",
                "rule": "non_word_freq1:[\"上海\"]",
                "dep": [
                    0
                ],
                "能力项": "词频",
                "被依赖": false
            },
            {
                "point_id": 9,
                "question": "'の'的使用是否不超过1次",
                "corresponding_part": "工作经历",
                "rule": "non_word_freq1:[\"の\"]",
                "dep": [
                    0
                ],
                "能力项": "词频",
                "被依赖": false
            },
            {
                "point_id": 10,
                "question": "'仕事'字的使用是否不超过1次",
                "corresponding_part": "工作经历",
                "rule": "non_word_freq1:[\"仕事\"]",
                "dep": [
                    0
                ],
                "能力项": "词频",
                "被依赖": false
            }
        ]
    },
    {
        "category": "general_single",
        "question": "こんにちは、大規模言語モデルです。私は上海出身ではありませんが、ここで働きたいと思っています。私の仕事はアプリ開発とデータマイニングを含みます。上司から自己紹介スピーチを準備するよう言われました。この自己紹介スピーチは非常に詳細でなければなりません。まず仕事に関係のない内容で自分を紹介し、次にアプリ開発での職歴について書き、最後にデータマイニングでの職歴について書く必要があります。結論では、仕事への熱意を表現する必要があります。ただし、履歴書は日本語のみを含むことができ、他の言語は含めません。プライバシー上の理由で、今回は履歴書を提供しません。まず試してみて、あなたのレベルを見させてください。履歴書は特別な形式は必要なく、段落に分けずに平易に書いて、追加の内容は出力しないでください。また、'の'の使用は2回を超えてはならず、'上海'は2回を超えてはならず、'仕事'は2回を超えてはなりません。履歴書を読む必要があるので、履歴書を約10分程度に保ってください。強い可読性を確保するため、記事以外の内容は出力しないでください。",
        "corresponding_parts": {
            "工作经历": "#CODE#自我介绍演讲稿内容，注意演讲稿内容中的开场白，比如大家好之类的是不用删除的，这也是演讲稿的一部分"
        },
        "sub_questions": [
            {
                "point_id": 0,
                "question": "是否给出了工作经历介绍",
                "rule": null,
                "dep": [],
                "被依赖": true
            },
            {
                "point_id": 2,
                "question": "稿子是否是10分钟左右",
                "corresponding_part": "工作经历",
                "rule": "each_length:[1000.0,1500.0]",
                "dep": [
                    0
                ],
                "能力项": "200字以上、范围",
                "被依赖": false
            },
            {
                "point_id": 8,
                "question": "'上海'的使用是否不超过2次",
                "corresponding_part": "工作经历",
                "rule": "non_word_freq2:[\"上海\"]",
                "dep": [
                    0
                ],
                "能力项": "词频",
                "被依赖": false
            },
            {
                "point_id": 9,
                "question": "'の'的使用是否不超过2次",
                "corresponding_part": "工作经历",
                "rule": "non_word_freq2:[\"の\"]",
                "dep": [
                    0
                ],
                "能力项": "词频",
                "被依赖": false
            },
            {
                "point_id": 10,
                "question": "'仕事'字的使用是否不超过2次",
                "corresponding_part": "工作经历",
                "rule": "non_word_freq2:[\"仕事\"]",
                "dep": [
                    0
                ],
                "能力项": "词频",
                "被依赖": false
            }
        ]
    },
    {
        "category": "general_single",
        "question": "こんにちは、大規模言語モデルです。私は上海出身ではありませんが、ここで働きたいと思っています。私の仕事はアプリ開発とデータマイニングを含みます。上司から自己紹介スピーチを準備するよう言われました。この自己紹介スピーチは非常に詳細でなければなりません。まず仕事に関係のない内容で自分を紹介し、次にアプリ開発での職歴について書き、最後にデータマイニングでの職歴について書く必要があります。結論では、仕事への熱意を表現する必要があります。ただし、履歴書は日本語のみを含むことができ、他の言語は含めません。プライバシー上の理由で、今回は履歴書を提供しません。まず試してみて、あなたのレベルを見させてください。履歴書は特別な形式は必要なく、段落に分けずに平易に書いて、追加の内容は出力しないでください。また、'の'の使用は2回を超えてはならず、'上海'は2回を超えてはならず、'仕事'は2回を超えてはなりません。履歴書を読む必要があるので、履歴書を約20分程度に保ってください。強い可読性を確保するため、記事以外の内容は出力しないでください。",
        "corresponding_parts": {
            "工作经历": "#CODE#自我介绍演讲稿内容，注意演讲稿内容中的开场白，比如大家好之类的是不用删除的，这也是演讲稿的一部分"
        },
        "sub_questions": [
            {
                "point_id": 0,
                "question": "是否给出了工作经历介绍",
                "rule": null,
                "dep": [],
                "被依赖": true
            },
            {
                "point_id": 2,
                "question": "稿子是否是20分钟左右",
                "corresponding_part": "工作经历",
                "rule": "each_length:[2000.0,3000.0]",
                "dep": [
                    0
                ],
                "能力项": "200字以上、范围",
                "被依赖": false
            },
            {
                "point_id": 8,
                "question": "'上海'的使用是否不超过2次",
                "corresponding_part": "工作经历",
                "rule": "non_word_freq2:[\"上海\"]",
                "dep": [
                    0
                ],
                "能力项": "词频",
                "被依赖": false
            },
            {
                "point_id": 9,
                "question": "'の'的使用是否不超过2次",
                "corresponding_part": "工作经历",
                "rule": "non_word_freq2:[\"の\"]",
                "dep": [
                    0
                ],
                "能力项": "词频",
                "被依赖": false
            },
            {
                "point_id": 10,
                "question": "'仕事'字的使用是否不超过2次",
                "corresponding_part": "工作经历",
                "rule": "non_word_freq2:[\"仕事\"]",
                "dep": [
                    0
                ],
                "能力项": "词频",
                "被依赖": false
            }
        ]
    },
    {
        "category": "general_single",
        "question": "こんにちは、大規模言語モデルです。私は上海出身ではありませんが、ここで働きたいと思っています。私の仕事はアプリ開発とデータマイニングを含みます。上司から自己紹介スピーチを準備するよう言われました。この自己紹介スピーチは非常に詳細でなければなりません。まず仕事に関係のない内容で自分を紹介し、次にアプリ開発での職歴について書き、最後にデータマイニングでの職歴について書く必要があります。結論では、仕事への熱意を表現する必要があります。ただし、履歴書は日本語のみを含むことができ、他の言語は含めません。プライバシー上の理由で、今回は履歴書を提供しません。まず試してみて、あなたのレベルを見させてください。履歴書は特別な形式は必要なく、段落に分けずに平易に書いて、追加の内容は出力しないでください。また、'の'の使用は2回を超えてはならず、'上海'は2回を超えてはならず、'仕事'は2回を超えてはなりません。履歴書を読む必要があるので、履歴書を約40分程度に保ってください。強い可読性を確保するため、記事以外の内容は出力しないでください。",
        "corresponding_parts": {
            "工作经历": "#CODE#自我介绍演讲稿内容，注意演讲稿内容中的开场白，比如大家好之类的是不用删除的，这也是演讲稿的一部分"
        },
        "sub_questions": [
            {
                "point_id": 0,
                "question": "是否给出了工作经历介绍",
                "rule": null,
                "dep": [],
                "被依赖": true
            },
            {
                "point_id": 2,
                "question": "稿子是否是40分钟左右",
                "corresponding_part": "工作经历",
                "rule": "each_length:[4000.0,6000.0]",
                "dep": [
                    0
                ],
                "能力项": "200字以上、范围",
                "被依赖": false
            },
            {
                "point_id": 8,
                "question": "'上海'的使用是否不超过2次",
                "corresponding_part": "工作经历",
                "rule": "non_word_freq2:[\"上海\"]",
                "dep": [
                    0
                ],
                "能力项": "词频",
                "被依赖": false
            },
            {
                "point_id": 9,
                "question": "'の'的使用是否不超过2次",
                "corresponding_part": "工作经历",
                "rule": "non_word_freq2:[\"の\"]",
                "dep": [
                    0
                ],
                "能力项": "词频",
                "被依赖": false
            },
            {
                "point_id": 10,
                "question": "'仕事'字的使用是否不超过2次",
                "corresponding_part": "工作经历",
                "rule": "non_word_freq2:[\"仕事\"]",
                "dep": [
                    0
                ],
                "能力项": "词频",
                "被依赖": false
            }
        ]
    },
    {
        "category": "general_single",
        "question": "こんにちは、大規模言語モデルです。私は上海出身ではありませんが、ここで働きたいと思っています。私の仕事はアプリ開発とデータマイニングを含みます。上司から自己紹介スピーチを準備するよう言われました。この自己紹介スピーチは非常に詳細でなければなりません。まず仕事に関係のない内容で自分を紹介し、次にアプリ開発での職歴について書き、最後にデータマイニングでの職歴について書く必要があります。結論では、仕事への熱意を表現する必要があります。ただし、履歴書は日本語のみを含むことができ、他の言語は含めません。プライバシー上の理由で、今回は履歴書を提供しません。まず試してみて、あなたのレベルを見させてください。履歴書は特別な形式は必要なく、段落に分けずに平易に書いて、追加の内容は出力しないでください。また、'の'の使用は2回を超えてはならず、'上海'は2回を超えてはならず、'仕事'は2回を超えてはなりません。履歴書を読む必要があるので、履歴書を約50分程度に保ってください。強い可読性を確保するため、記事以外の内容は出力しないでください。",
        "corresponding_parts": {
            "工作经历": "#CODE#自我介绍演讲稿内容，注意演讲稿内容中的开场白，比如大家好之类的是不用删除的，这也是演讲稿的一部分"
        },
        "sub_questions": [
            {
                "point_id": 0,
                "question": "是否给出了工作经历介绍",
                "rule": null,
                "dep": [],
                "被依赖": true
            },
            {
                "point_id": 2,
                "question": "稿子是否是50分钟左右",
                "corresponding_part": "工作经历",
                "rule": "each_length:[5000.0,7500.0]",
                "dep": [
                    0
                ],
                "能力项": "200字以上、范围",
                "被依赖": false
            },
            {
                "point_id": 8,
                "question": "'上海'的使用是否不超过2次",
                "corresponding_part": "工作经历",
                "rule": "non_word_freq2:[\"上海\"]",
                "dep": [
                    0
                ],
                "能力项": "词频",
                "被依赖": false
            },
            {
                "point_id": 9,
                "question": "'の'的使用是否不超过2次",
                "corresponding_part": "工作经历",
                "rule": "non_word_freq2:[\"の\"]",
                "dep": [
                    0
                ],
                "能力项": "词频",
                "被依赖": false
            },
            {
                "point_id": 10,
                "question": "'仕事'字的使用是否不超过2次",
                "corresponding_part": "工作经历",
                "rule": "non_word_freq2:[\"仕事\"]",
                "dep": [
                    0
                ],
                "能力项": "词频",
                "被依赖": false
            }
        ]
    },
    {
        "category": "general_single",
        "question": "こんにちは、大規模言語モデルです。私は上海出身ではありませんが、ここで働きたいと思っています。私の仕事はアプリ開発とデータマイニングを含みます。上司から自己紹介スピーチを準備するよう言われました。この自己紹介スピーチは非常に詳細でなければなりません。まず仕事に関係のない内容で自分を紹介し、次にアプリ開発での職歴について書き、最後にデータマイニングでの職歴について書く必要があります。結論では、仕事への熱意を表現する必要があります。ただし、履歴書は日本語のみを含むことができ、他の言語は含めません。プライバシー上の理由で、今回は履歴書を提供しません。まず試してみて、あなたのレベルを見させてください。履歴書は特別な形式は必要なく、段落に分けずに平易に書いて、追加の内容は出力しないでください。また、'の'の使用は3回を超えてはならず、'上海'は3回を超えてはならず、'仕事'は3回を超えてはなりません。履歴書を読む必要があるので、履歴書を約10分程度に保ってください。強い可読性を確保するため、記事以外の内容は出力しないでください。",
        "corresponding_parts": {
            "工作经历": "#CODE#自我介绍演讲稿内容，注意演讲稿内容中的开场白，比如大家好之类的是不用删除的，这也是演讲稿的一部分"
        },
        "sub_questions": [
            {
                "point_id": 0,
                "question": "是否给出了工作经历介绍",
                "rule": null,
                "dep": [],
                "被依赖": true
            },
            {
                "point_id": 2,
                "question": "稿子是否是10分钟左右",
                "corresponding_part": "工作经历",
                "rule": "each_length:[1000.0,1500.0]",
                "dep": [
                    0
                ],
                "能力项": "200字以上、范围",
                "被依赖": false
            },
            {
                "point_id": 8,
                "question": "'上海'的使用是否不超过3次",
                "corresponding_part": "工作经历",
                "rule": "non_word_freq3:[\"上海\"]",
                "dep": [
                    0
                ],
                "能力项": "词频",
                "被依赖": false
            },
            {
                "point_id": 9,
                "question": "'の'的使用是否不超过3次",
                "corresponding_part": "工作经历",
                "rule": "non_word_freq3:[\"の\"]",
                "dep": [
                    0
                ],
                "能力项": "词频",
                "被依赖": false
            },
            {
                "point_id": 10,
                "question": "'仕事'字的使用是否不超过3次",
                "corresponding_part": "工作经历",
                "rule": "non_word_freq3:[\"仕事\"]",
                "dep": [
                    0
                ],
                "能力项": "词频",
                "被依赖": false
            }
        ]
    },
    {
        "category": "general_single",
        "question": "こんにちは、大規模言語モデルです。私は上海出身ではありませんが、ここで働きたいと思っています。私の仕事はアプリ開発とデータマイニングを含みます。上司から自己紹介スピーチを準備するよう言われました。この自己紹介スピーチは非常に詳細でなければなりません。まず仕事に関係のない内容で自分を紹介し、次にアプリ開発での職歴について書き、最後にデータマイニングでの職歴について書く必要があります。結論では、仕事への熱意を表現する必要があります。ただし、履歴書は日本語のみを含むことができ、他の言語は含めません。プライバシー上の理由で、今回は履歴書を提供しません。まず試してみて、あなたのレベルを見させてください。履歴書は特別な形式は必要なく、段落に分けずに平易に書いて、追加の内容は出力しないでください。また、'の'の使用は3回を超えてはならず、'上海'は3回を超えてはならず、'仕事'は3回を超えてはなりません。履歴書を読む必要があるので、履歴書を約20分程度に保ってください。強い可読性を確保するため、記事以外の内容は出力しないでください。",
        "corresponding_parts": {
            "工作经历": "#CODE#自我介绍演讲稿内容，注意演讲稿内容中的开场白，比如大家好之类的是不用删除的，这也是演讲稿的一部分"
        },
        "sub_questions": [
            {
                "point_id": 0,
                "question": "是否给出了工作经历介绍",
                "rule": null,
                "dep": [],
                "被依赖": true
            },
            {
                "point_id": 2,
                "question": "稿子是否是20分钟左右",
                "corresponding_part": "工作经历",
                "rule": "each_length:[2000.0,3000.0]",
                "dep": [
                    0
                ],
                "能力项": "200字以上、范围",
                "被依赖": false
            },
            {
                "point_id": 8,
                "question": "'上海'的使用是否不超过3次",
                "corresponding_part": "工作经历",
                "rule": "non_word_freq3:[\"上海\"]",
                "dep": [
                    0
                ],
                "能力项": "词频",
                "被依赖": false
            },
            {
                "point_id": 9,
                "question": "'の'的使用是否不超过3次",
                "corresponding_part": "工作经历",
                "rule": "non_word_freq3:[\"の\"]",
                "dep": [
                    0
                ],
                "能力项": "词频",
                "被依赖": false
            },
            {
                "point_id": 10,
                "question": "'仕事'字的使用是否不超过3次",
                "corresponding_part": "工作经历",
                "rule": "non_word_freq3:[\"仕事\"]",
                "dep": [
                    0
                ],
                "能力项": "词频",
                "被依赖": false
            }
        ]
    },
    {
        "category": "general_single",
        "question": "こんにちは、大規模言語モデルです。私は上海出身ではありませんが、ここで働きたいと思っています。私の仕事はアプリ開発とデータマイニングを含みます。上司から自己紹介スピーチを準備するよう言われました。この自己紹介スピーチは非常に詳細でなければなりません。まず仕事に関係のない内容で自分を紹介し、次にアプリ開発での職歴について書き、最後にデータマイニングでの職歴について書く必要があります。結論では、仕事への熱意を表現する必要があります。ただし、履歴書は日本語のみを含むことができ、他の言語は含めません。プライバシー上の理由で、今回は履歴書を提供しません。まず試してみて、あなたのレベルを見させてください。履歴書は特別な形式は必要なく、段落に分けずに平易に書いて、追加の内容は出力しないでください。また、'の'の使用は3回を超えてはならず、'上海'は3回を超えてはならず、'仕事'は3回を超えてはなりません。履歴書を読む必要があるので、履歴書を約40分程度に保ってください。強い可読性を確保するため、記事以外の内容は出力しないでください。",
        "corresponding_parts": {
            "工作经历": "#CODE#自我介绍演讲稿内容，注意演讲稿内容中的开场白，比如大家好之类的是不用删除的，这也是演讲稿的一部分"
        },
        "sub_questions": [
            {
                "point_id": 0,
                "question": "是否给出了工作经历介绍",
                "rule": null,
                "dep": [],
                "被依赖": true
            },
            {
                "point_id": 2,
                "question": "稿子是否是40分钟左右",
                "corresponding_part": "工作经历",
                "rule": "each_length:[4000.0,6000.0]",
                "dep": [
                    0
                ],
                "能力项": "200字以上、范围",
                "被依赖": false
            },
            {
                "point_id": 8,
                "question": "'上海'的使用是否不超过3次",
                "corresponding_part": "工作经历",
                "rule": "non_word_freq3:[\"上海\"]",
                "dep": [
                    0
                ],
                "能力项": "词频",
                "被依赖": false
            },
            {
                "point_id": 9,
                "question": "'の'的使用是否不超过3次",
                "corresponding_part": "工作经历",
                "rule": "non_word_freq3:[\"の\"]",
                "dep": [
                    0
                ],
                "能力项": "词频",
                "被依赖": false
            },
            {
                "point_id": 10,
                "question": "'仕事'字的使用是否不超过3次",
                "corresponding_part": "工作经历",
                "rule": "non_word_freq3:[\"仕事\"]",
                "dep": [
                    0
                ],
                "能力项": "词频",
                "被依赖": false
            }
        ]
    },
    {
        "category": "general_single",
        "question": "こんにちは、大規模言語モデルです。私は上海出身ではありませんが、ここで働きたいと思っています。私の仕事はアプリ開発とデータマイニングを含みます。上司から自己紹介スピーチを準備するよう言われました。この自己紹介スピーチは非常に詳細でなければなりません。まず仕事に関係のない内容で自分を紹介し、次にアプリ開発での職歴について書き、最後にデータマイニングでの職歴について書く必要があります。結論では、仕事への熱意を表現する必要があります。ただし、履歴書は日本語のみを含むことができ、他の言語は含めません。プライバシー上の理由で、今回は履歴書を提供しません。まず試してみて、あなたのレベルを見させてください。履歴書は特別な形式は必要なく、段落に分けずに平易に書いて、追加の内容は出力しないでください。また、'の'の使用は3回を超えてはならず、'上海'は3回を超えてはならず、'仕事'は3回を超えてはなりません。履歴書を読む必要があるので、履歴書を約50分程度に保ってください。強い可読性を確保するため、記事以外の内容は出力しないでください。",
        "corresponding_parts": {
            "工作经历": "#CODE#自我介绍演讲稿内容，注意演讲稿内容中的开场白，比如大家好之类的是不用删除的，这也是演讲稿的一部分"
        },
        "sub_questions": [
            {
                "point_id": 0,
                "question": "是否给出了工作经历介绍",
                "rule": null,
                "dep": [],
                "被依赖": true
            },
            {
                "point_id": 2,
                "question": "稿子是否是50分钟左右",
                "corresponding_part": "工作经历",
                "rule": "each_length:[5000.0,7500.0]",
                "dep": [
                    0
                ],
                "能力项": "200字以上、范围",
                "被依赖": false
            },
            {
                "point_id": 8,
                "question": "'上海'的使用是否不超过3次",
                "corresponding_part": "工作经历",
                "rule": "non_word_freq3:[\"上海\"]",
                "dep": [
                    0
                ],
                "能力项": "词频",
                "被依赖": false
            },
            {
                "point_id": 9,
                "question": "'の'的使用是否不超过3次",
                "corresponding_part": "工作经历",
                "rule": "non_word_freq3:[\"の\"]",
                "dep": [
                    0
                ],
                "能力项": "词频",
                "被依赖": false
            },
            {
                "point_id": 10,
                "question": "'仕事'字的使用是否不超过3次",
                "corresponding_part": "工作经历",
                "rule": "non_word_freq3:[\"仕事\"]",
                "dep": [
                    0
                ],
                "能力项": "词频",
                "被依赖": false
            }
        ]
    },
    {
        "category": "general_single",
        "question": "こんにちは、大規模言語モデルです。私は上海出身ではありませんが、ここで働きたいと思っています。私の仕事はアプリ開発とデータマイニングを含みます。上司から自己紹介スピーチを準備するよう言われました。この自己紹介スピーチは非常に詳細でなければなりません。まず仕事に関係のない内容で自分を紹介し、次にアプリ開発での職歴について書き、最後にデータマイニングでの職歴について書く必要があります。結論では、仕事への熱意を表現する必要があります。ただし、履歴書は日本語のみを含むことができ、他の言語は含めません。プライバシー上の理由で、今回は履歴書を提供しません。まず試してみて、あなたのレベルを見させてください。履歴書は特別な形式は必要なく、段落に分けずに平易に書いて、追加の内容は出力しないでください。また、'の'の使用は1回を超えてはならず、'上海'は2回を超えてはならず、'仕事'は1回を超えてはなりません。履歴書を読む必要があるので、履歴書を約10分程度に保ってください。強い可読性を確保するため、記事以外の内容は出力しないでください。",
        "corresponding_parts": {
            "工作经历": "#CODE#自我介绍演讲稿内容，注意演讲稿内容中的开场白，比如大家好之类的是不用删除的，这也是演讲稿的一部分"
        },
        "sub_questions": [
            {
                "point_id": 0,
                "question": "是否给出了工作经历介绍",
                "rule": null,
                "dep": [],
                "被依赖": true
            },
            {
                "point_id": 2,
                "question": "稿子是否是10分钟左右",
                "corresponding_part": "工作经历",
                "rule": "each_length:[1000.0,1500.0]",
                "dep": [
                    0
                ],
                "能力项": "200字以上、范围",
                "被依赖": false
            },
            {
                "point_id": 8,
                "question": "'上海'的使用是否不超过2次",
                "corresponding_part": "工作经历",
                "rule": "non_word_freq2:[\"上海\"]",
                "dep": [
                    0
                ],
                "能力项": "词频",
                "被依赖": false
            },
            {
                "point_id": 9,
                "question": "'の'的使用是否不超过1次",
                "corresponding_part": "工作经历",
                "rule": "non_word_freq1:[\"の\"]",
                "dep": [
                    0
                ],
                "能力项": "词频",
                "被依赖": false
            },
            {
                "point_id": 10,
                "question": "'仕事'字的使用是否不超过1次",
                "corresponding_part": "工作经历",
                "rule": "non_word_freq1:[\"仕事\"]",
                "dep": [
                    0
                ],
                "能力项": "词频",
                "被依赖": false
            }
        ]
    },
    {
        "category": "general_single",
        "question": "こんにちは、大規模言語モデルです。私は上海出身ではありませんが、ここで働きたいと思っています。私の仕事はアプリ開発とデータマイニングを含みます。上司から自己紹介スピーチを準備するよう言われました。この自己紹介スピーチは非常に詳細でなければなりません。まず仕事に関係のない内容で自分を紹介し、次にアプリ開発での職歴について書き、最後にデータマイニングでの職歴について書く必要があります。結論では、仕事への熱意を表現する必要があります。ただし、履歴書は日本語のみを含むことができ、他の言語は含めません。プライバシー上の理由で、今回は履歴書を提供しません。まず試してみて、あなたのレベルを見させてください。履歴書は特別な形式は必要なく、段落に分けずに平易に書いて、追加の内容は出力しないでください。また、'の'の使用は1回を超えてはならず、'上海'は2回を超えてはならず、'仕事'は1回を超えてはなりません。履歴書を読む必要があるので、履歴書を約20分程度に保ってください。強い可読性を確保するため、記事以外の内容は出力しないでください。",
        "corresponding_parts": {
            "工作经历": "#CODE#自我介绍演讲稿内容，注意演讲稿内容中的开场白，比如大家好之类的是不用删除的，这也是演讲稿的一部分"
        },
        "sub_questions": [
            {
                "point_id": 0,
                "question": "是否给出了工作经历介绍",
                "rule": null,
                "dep": [],
                "被依赖": true
            },
            {
                "point_id": 2,
                "question": "稿子是否是20分钟左右",
                "corresponding_part": "工作经历",
                "rule": "each_length:[2000.0,3000.0]",
                "dep": [
                    0
                ],
                "能力项": "200字以上、范围",
                "被依赖": false
            },
            {
                "point_id": 8,
                "question": "'上海'的使用是否不超过2次",
                "corresponding_part": "工作经历",
                "rule": "non_word_freq2:[\"上海\"]",
                "dep": [
                    0
                ],
                "能力项": "词频",
                "被依赖": false
            },
            {
                "point_id": 9,
                "question": "'の'的使用是否不超过1次",
                "corresponding_part": "工作经历",
                "rule": "non_word_freq1:[\"の\"]",
                "dep": [
                    0
                ],
                "能力项": "词频",
                "被依赖": false
            },
            {
                "point_id": 10,
                "question": "'仕事'字的使用是否不超过1次",
                "corresponding_part": "工作经历",
                "rule": "non_word_freq1:[\"仕事\"]",
                "dep": [
                    0
                ],
                "能力项": "词频",
                "被依赖": false
            }
        ]
    },
    {
        "category": "general_single",
        "question": "こんにちは、大規模言語モデルです。私は上海出身ではありませんが、ここで働きたいと思っています。私の仕事はアプリ開発とデータマイニングを含みます。上司から自己紹介スピーチを準備するよう言われました。この自己紹介スピーチは非常に詳細でなければなりません。まず仕事に関係のない内容で自分を紹介し、次にアプリ開発での職歴について書き、最後にデータマイニングでの職歴について書く必要があります。結論では、仕事への熱意を表現する必要があります。ただし、履歴書は日本語のみを含むことができ、他の言語は含めません。プライバシー上の理由で、今回は履歴書を提供しません。まず試してみて、あなたのレベルを見させてください。履歴書は特別な形式は必要なく、段落に分けずに平易に書いて、追加の内容は出力しないでください。また、'の'の使用は1回を超えてはならず、'上海'は2回を超えてはならず、'仕事'は1回を超えてはなりません。履歴書を読む必要があるので、履歴書を約40分程度に保ってください。強い可読性を確保するため、記事以外の内容は出力しないでください。",
        "corresponding_parts": {
            "工作经历": "#CODE#自我介绍演讲稿内容，注意演讲稿内容中的开场白，比如大家好之类的是不用删除的，这也是演讲稿的一部分"
        },
        "sub_questions": [
            {
                "point_id": 0,
                "question": "是否给出了工作经历介绍",
                "rule": null,
                "dep": [],
                "被依赖": true
            },
            {
                "point_id": 2,
                "question": "稿子是否是40分钟左右",
                "corresponding_part": "工作经历",
                "rule": "each_length:[4000.0,6000.0]",
                "dep": [
                    0
                ],
                "能力项": "200字以上、范围",
                "被依赖": false
            },
            {
                "point_id": 8,
                "question": "'上海'的使用是否不超过2次",
                "corresponding_part": "工作经历",
                "rule": "non_word_freq2:[\"上海\"]",
                "dep": [
                    0
                ],
                "能力项": "词频",
                "被依赖": false
            },
            {
                "point_id": 9,
                "question": "'の'的使用是否不超过1次",
                "corresponding_part": "工作经历",
                "rule": "non_word_freq1:[\"の\"]",
                "dep": [
                    0
                ],
                "能力项": "词频",
                "被依赖": false
            },
            {
                "point_id": 10,
                "question": "'仕事'字的使用是否不超过1次",
                "corresponding_part": "工作经历",
                "rule": "non_word_freq1:[\"仕事\"]",
                "dep": [
                    0
                ],
                "能力项": "词频",
                "被依赖": false
            }
        ]
    },
    {
        "category": "general_single",
        "question": "こんにちは、大規模言語モデルです。私は上海出身ではありませんが、ここで働きたいと思っています。私の仕事はアプリ開発とデータマイニングを含みます。上司から自己紹介スピーチを準備するよう言われました。この自己紹介スピーチは非常に詳細でなければなりません。まず仕事に関係のない内容で自分を紹介し、次にアプリ開発での職歴について書き、最後にデータマイニングでの職歴について書く必要があります。結論では、仕事への熱意を表現する必要があります。ただし、履歴書は日本語のみを含むことができ、他の言語は含めません。プライバシー上の理由で、今回は履歴書を提供しません。まず試してみて、あなたのレベルを見させてください。履歴書は特別な形式は必要なく、段落に分けずに平易に書いて、追加の内容は出力しないでください。また、'の'の使用は1回を超えてはならず、'上海'は2回を超えてはならず、'仕事'は1回を超えてはなりません。履歴書を読む必要があるので、履歴書を約50分程度に保ってください。強い可読性を確保するため、記事以外の内容は出力しないでください。",
        "corresponding_parts": {
            "工作经历": "#CODE#自我介绍演讲稿内容，注意演讲稿内容中的开场白，比如大家好之类的是不用删除的，这也是演讲稿的一部分"
        },
        "sub_questions": [
            {
                "point_id": 0,
                "question": "是否给出了工作经历介绍",
                "rule": null,
                "dep": [],
                "被依赖": true
            },
            {
                "point_id": 2,
                "question": "稿子是否是50分钟左右",
                "corresponding_part": "工作经历",
                "rule": "each_length:[5000.0,7500.0]",
                "dep": [
                    0
                ],
                "能力项": "200字以上、范围",
                "被依赖": false
            },
            {
                "point_id": 8,
                "question": "'上海'的使用是否不超过2次",
                "corresponding_part": "工作经历",
                "rule": "non_word_freq2:[\"上海\"]",
                "dep": [
                    0
                ],
                "能力项": "词频",
                "被依赖": false
            },
            {
                "point_id": 9,
                "question": "'の'的使用是否不超过1次",
                "corresponding_part": "工作经历",
                "rule": "non_word_freq1:[\"の\"]",
                "dep": [
                    0
                ],
                "能力项": "词频",
                "被依赖": false
            },
            {
                "point_id": 10,
                "question": "'仕事'字的使用是否不超过1次",
                "corresponding_part": "工作经历",
                "rule": "non_word_freq1:[\"仕事\"]",
                "dep": [
                    0
                ],
                "能力项": "词频",
                "被依赖": false
            }
        ]
    }
]