[
    {
        "category": "general_single",
        "question": "请您选出以下内容中的同音词以及特定部首的字，并用这些词和字写一篇，描写荷塘月色的文章。【在晨曦初升的时刻，水面如镜，倒映着熠熠生辉的霞光，远处的山屿若隐若现。水鸟掠过，羽翼轻拂，仿佛在湖心写下意义深远的诗句。湖畔柳丝轻摆，仿佛在对这喧嚣尘世提出温和的异议。它用自己的方式诠释着时光——不是激烈的抗争，而是如意译般的转化，将内心的不安化作诗意的舞蹈，在风中低语着属于自然的哲学。微风拂过，令人思忖，悄然唤醒沉睡已久的情愫。远处雄峰屹立，山峦叠嶂，岚气舒卷，山色漫衍,如同岁月的画卷。每一寸光影都在诉说着生命的意义，而每一朵花的开放，都有它独特的意义。阳光透过云层，照亮了无数微小的欢愉。大地静默，万物各自用自己的方式诠释着时光的温柔，怡然生长，静静守候。万物的心志与自然的情感交融，在这静谧的清晨,人们心怀喜悦开启新的一天。】要求如下：1.从文段中找出读音相同的二字词语，发音包括声调完全相同，在你的文章中需要用到至少4个文段中这样的同音词。\n2.从文段中找出部首是[言部]的汉字，并在你的文章中至少用到7个。\n3.你的文章字数需要在800字左右，左右意味着允许上下浮动10%。 \n4.关键词\"月光\",\"这\",\"意义\"在你的文章中使用不能超过2次。请你直接给出文章。",
        "corresponding_parts": {
            "文章": "#CODE#所有模型输出的文章,不进行分割"
        },
        "sub_questions": [
            {
                "point_id": 0,
                "question": "是否给出了文章",
                "rule": null,
                "dep": [],
                "被依赖": true
            },
            {
                "point_id": 1,
                "question": "文章是否描写了荷塘月色",
                "rule": null,
                "dep": [
                    0
                ],
                "能力项": "主题约束",
                "被依赖": false
            },
            {
                "point_id": 2,
                "question": "文章是否在800字左右",
                "corresponding_part": "文章",
                "rule": "each_length:[720.0,880.0]",
                "dep": [
                    0
                ],
                "能力项": "200字以上、范围",
                "被依赖": false
            },
            {
                "point_id": 3,
                "question": "文章中是否包含至少4个文段中的同音词。",
                "corresponding_part": "文章",
                "rule": "any_keywords4:[\"熠熠\",\"意义\",\"异议\",\"意译\"]",
                "dep": [
                    0
                ],
                "能力项": "中文：同音词",
                "被依赖": false
            },
            {
                "point_id": 4,
                "question": "文章中是否至少用到7个文段中[言部]的汉字",
                "corresponding_part": "文章",
                "rule": "any_keywords7:[\"诗\",\"议\",\"诠\",\"译\",\"语\",\"诉\",\"说\",\"谧\"]",
                "dep": [
                    0
                ],
                "能力项": "结构词",
                "被依赖": false
            },
            {
                "point_id": 5,
                "question": "关键词\"月光\",\"这\",\"意义\"在文章中是否出现不超过2次",
                "corresponding_part": "文章",
                "rule": "non_word_freq2:[\"月光\",\"这\",\"意义\"]",
                "dep": [
                    0
                ],
                "能力项": "词频",
                "被依赖": false
            }
        ]
    },
    {
        "category": "general_single",
        "question": "请您选出以下内容中的同音词以及特定部首的字，并用这些词和字写一篇，描写荷塘月色的文章。【在晨曦初升的时刻，水面如镜，倒映着熠熠生辉的霞光，远处的山屿若隐若现。水鸟掠过，羽翼轻拂，仿佛在湖心写下意义深远的诗句。湖畔柳丝轻摆，仿佛在对这喧嚣尘世提出温和的异议。它用自己的方式诠释着时光——不是激烈的抗争，而是如意译般的转化，将内心的不安化作诗意的舞蹈，在风中低语着属于自然的哲学。微风拂过，令人思忖，悄然唤醒沉睡已久的情愫。远处雄峰屹立，山峦叠嶂，岚气舒卷，山色漫衍,如同岁月的画卷。每一寸光影都在诉说着生命的意义，而每一朵花的开放，都有它独特的意义。阳光透过云层，照亮了无数微小的欢愉。大地静默，万物各自用自己的方式诠释着时光的温柔，怡然生长，静静守候。万物的心志与自然的情感交融，在这静谧的清晨,人们心怀喜悦开启新的一天。】要求如下：1.从文段中找出读音相同的二字词语，发音包括声调完全相同，在你的文章中需要用到至少3个文段中这样的同音词。\n2.从文段中找出部首是[扌部]的汉字，并在你的文章中至少用到5个。\n3.你的文章字数需要在700字左右，左右意味着允许上下浮动10%。 \n4.关键词\"自然\",\"天然\",\"夜色\"在你的文章中使用不能超过3次。请你直接给出文章。",
        "corresponding_parts": {
            "文章": "#CODE#所有模型输出的文章,不进行分割"
        },
        "sub_questions": [
            {
                "point_id": 0,
                "question": "是否给出了文章",
                "rule": null,
                "dep": [],
                "被依赖": true
            },
            {
                "point_id": 1,
                "question": "文章是否描写了荷塘月色",
                "rule": null,
                "dep": [
                    0
                ],
                "能力项": "主题约束",
                "被依赖": false
            },
            {
                "point_id": 2,
                "question": "文章是否在700字左右",
                "corresponding_part": "文章",
                "rule": "each_length:[630.0,770.0]",
                "dep": [
                    0
                ],
                "能力项": "200字以上、范围",
                "被依赖": false
            },
            {
                "point_id": 3,
                "question": "文章中是否包含至少3个文段中的同音词。",
                "corresponding_part": "文章",
                "rule": "any_keywords3:[\"熠熠\",\"意义\",\"异议\",\"意译\"]",
                "dep": [
                    0
                ],
                "能力项": "中文：同音词",
                "被依赖": false
            },
            {
                "point_id": 4,
                "question": "文章中是否至少用到5个文段中[扌部]的汉字",
                "corresponding_part": "文章",
                "rule": "any_keywords5:[\"掠\",\"拂\",\"摆\",\"提\",\"抗\"]",
                "dep": [
                    0
                ],
                "能力项": "结构词",
                "被依赖": false
            },
            {
                "point_id": 5,
                "question": "关键词\"自然\",\"天然\",\"夜色\"在文章中是否出现不超过3次",
                "corresponding_part": "文章",
                "rule": "non_word_freq3:[\"自然\",\"天然\",\"夜色\"]",
                "dep": [
                    0
                ],
                "能力项": "词频",
                "被依赖": false
            }
        ]
    },
    {
        "category": "general_single",
        "question": "请您选出以下内容中的同音词以及特定部首的字，并用这些词和字写一篇，描写荷塘月色的文章。【在晨曦初升的时刻，水面如镜，倒映着熠熠生辉的霞光，远处的山屿若隐若现。水鸟掠过，羽翼轻拂，仿佛在湖心写下意义深远的诗句。湖畔柳丝轻摆，仿佛在对这喧嚣尘世提出温和的异议。它用自己的方式诠释着时光——不是激烈的抗争，而是如意译般的转化，将内心的不安化作诗意的舞蹈，在风中低语着属于自然的哲学。微风拂过，令人思忖，悄然唤醒沉睡已久的情愫。远处雄峰屹立，山峦叠嶂，岚气舒卷，山色漫衍,如同岁月的画卷。每一寸光影都在诉说着生命的意义，而每一朵花的开放，都有它独特的意义。阳光透过云层，照亮了无数微小的欢愉。大地静默，万物各自用自己的方式诠释着时光的温柔，怡然生长，静静守候。万物的心志与自然的情感交融，在这静谧的清晨,人们心怀喜悦开启新的一天。】要求如下：1.从文段中找出读音相同的二字词语，发音包括声调完全相同，在你的文章中需要用到至少4个文段中这样的同音词。\n2.从文段中找出部首是[言部]的汉字，并在你的文章中至少用到8个。\n3.你的文章字数需要在500字左右，左右意味着允许上下浮动10%。 \n4.关键词\"情感\",\"感情\",\"水面\"在你的文章中使用不能超过1次。请你直接给出文章。",
        "corresponding_parts": {
            "文章": "#CODE#所有模型输出的文章,不进行分割"
        },
        "sub_questions": [
            {
                "point_id": 0,
                "question": "是否给出了文章",
                "rule": null,
                "dep": [],
                "被依赖": true
            },
            {
                "point_id": 1,
                "question": "文章是否描写了荷塘月色",
                "rule": null,
                "dep": [
                    0
                ],
                "能力项": "主题约束",
                "被依赖": false
            },
            {
                "point_id": 2,
                "question": "文章是否在500字左右",
                "corresponding_part": "文章",
                "rule": "each_length:[450.0,550.0]",
                "dep": [
                    0
                ],
                "能力项": "200字以上、范围",
                "被依赖": false
            },
            {
                "point_id": 3,
                "question": "文章中是否包含至少4个文段中的同音词。",
                "corresponding_part": "文章",
                "rule": "any_keywords4:[\"熠熠\",\"意义\",\"异议\",\"意译\"]",
                "dep": [
                    0
                ],
                "能力项": "中文：同音词",
                "被依赖": false
            },
            {
                "point_id": 4,
                "question": "文章中是否至少用到8个文段中[言部]的汉字",
                "corresponding_part": "文章",
                "rule": "any_keywords8:[\"诗\",\"议\",\"诠\",\"译\",\"语\",\"诉\",\"说\",\"谧\"]",
                "dep": [
                    0
                ],
                "能力项": "结构词",
                "被依赖": false
            },
            {
                "point_id": 5,
                "question": "关键词\"情感\",\"感情\",\"水面\"在文章中是否出现不超过1次",
                "corresponding_part": "文章",
                "rule": "non_word_freq1:[\"情感\",\"感情\",\"水面\"]",
                "dep": [
                    0
                ],
                "能力项": "词频",
                "被依赖": false
            }
        ]
    },
    {
        "category": "general_single",
        "question": "请您选出以下内容中的同音词以及特定部首的字，并用这些词和字写一篇，描写荷塘月色的文章。【在晨曦初升的时刻，水面如镜，倒映着熠熠生辉的霞光，远处的山屿若隐若现。水鸟掠过，羽翼轻拂，仿佛在湖心写下意义深远的诗句。湖畔柳丝轻摆，仿佛在对这喧嚣尘世提出温和的异议。它用自己的方式诠释着时光——不是激烈的抗争，而是如意译般的转化，将内心的不安化作诗意的舞蹈，在风中低语着属于自然的哲学。微风拂过，令人思忖，悄然唤醒沉睡已久的情愫。远处雄峰屹立，山峦叠嶂，岚气舒卷，山色漫衍,如同岁月的画卷。每一寸光影都在诉说着生命的意义，而每一朵花的开放，都有它独特的意义。阳光透过云层，照亮了无数微小的欢愉。大地静默，万物各自用自己的方式诠释着时光的温柔，怡然生长，静静守候。万物的心志与自然的情感交融，在这静谧的清晨,人们心怀喜悦开启新的一天。】要求如下：1.从文段中找出读音相同的二字词语，发音包括声调完全相同，在你的文章中需要用到至少3个文段中这样的同音词。\n2.从文段中找出部首是[忄部]的汉字，并在你的文章中至少用到8个。\n3.你的文章字数需要在650字左右，左右意味着允许上下浮动10%。 \n4.关键词\"诠释\",\"风\",\"荷塘\"在你的文章中使用不能超过3次。请你直接给出文章。",
        "corresponding_parts": {
            "文章": "#CODE#所有模型输出的文章,不进行分割"
        },
        "sub_questions": [
            {
                "point_id": 0,
                "question": "是否给出了文章",
                "rule": null,
                "dep": [],
                "被依赖": true
            },
            {
                "point_id": 1,
                "question": "文章是否描写了荷塘月色",
                "rule": null,
                "dep": [
                    0
                ],
                "能力项": "主题约束",
                "被依赖": false
            },
            {
                "point_id": 2,
                "question": "文章是否在650字左右",
                "corresponding_part": "文章",
                "rule": "each_length:[585.0,715.0]",
                "dep": [
                    0
                ],
                "能力项": "200字以上、范围",
                "被依赖": false
            },
            {
                "point_id": 3,
                "question": "文章中是否包含至少3个文段中的同音词。",
                "corresponding_part": "文章",
                "rule": "any_keywords3:[\"熠熠\",\"意义\",\"异议\",\"意译\"]",
                "dep": [
                    0
                ],
                "能力项": "中文：同音词",
                "被依赖": false
            },
            {
                "point_id": 4,
                "question": "文章中是否至少用到8个文段中[忄部]的汉字",
                "corresponding_part": "文章",
                "rule": "any_keywords8:[\"悄\",\"情\",\"愫\",\"愉\",\"忖\",\"怡\",\"怀\",\"悦\"]",
                "dep": [
                    0
                ],
                "能力项": "结构词",
                "被依赖": false
            },
            {
                "point_id": 5,
                "question": "关键词\"诠释\",\"风\",\"荷塘\"在文章中是否出现不超过3次",
                "corresponding_part": "文章",
                "rule": "non_word_freq3:[\"诠释\",\"风\",\"荷塘\"]",
                "dep": [
                    0
                ],
                "能力项": "词频",
                "被依赖": false
            }
        ]
    },
    {
        "category": "general_single",
        "question": "请您选出以下内容中的同音词以及特定部首的字，并用这些词和字写一篇，描写荷塘月色的文章。【在晨曦初升的时刻，水面如镜，倒映着熠熠生辉的霞光，远处的山屿若隐若现。水鸟掠过，羽翼轻拂，仿佛在湖心写下意义深远的诗句。湖畔柳丝轻摆，仿佛在对这喧嚣尘世提出温和的异议。它用自己的方式诠释着时光——不是激烈的抗争，而是如意译般的转化，将内心的不安化作诗意的舞蹈，在风中低语着属于自然的哲学。微风拂过，令人思忖，悄然唤醒沉睡已久的情愫。远处雄峰屹立，山峦叠嶂，岚气舒卷，山色漫衍,如同岁月的画卷。每一寸光影都在诉说着生命的意义，而每一朵花的开放，都有它独特的意义。阳光透过云层，照亮了无数微小的欢愉。大地静默，万物各自用自己的方式诠释着时光的温柔，怡然生长，静静守候。万物的心志与自然的情感交融，在这静谧的清晨,人们心怀喜悦开启新的一天。】要求如下：1.从文段中找出读音相同的二字词语，发音包括声调完全相同，在你的文章中需要用到至少4个文段中这样的同音词。\n2.从文段中找出部首是[山部]的汉字，并在你的文章中至少用到7个。\n3.你的文章字数需要在400字左右，左右意味着允许上下浮动10%。 \n4.关键词\"时光\",\"仿佛\",\"美\"在你的文章中使用不能超过1次。请你直接给出文章。",
        "corresponding_parts": {
            "文章": "#CODE#所有模型输出的文章,不进行分割"
        },
        "sub_questions": [
            {
                "point_id": 0,
                "question": "是否给出了文章",
                "rule": null,
                "dep": [],
                "被依赖": true
            },
            {
                "point_id": 1,
                "question": "文章是否描写了荷塘月色",
                "rule": null,
                "dep": [
                    0
                ],
                "能力项": "主题约束",
                "被依赖": false
            },
            {
                "point_id": 2,
                "question": "文章是否在400字左右",
                "corresponding_part": "文章",
                "rule": "each_length:[360.0,440.0]",
                "dep": [
                    0
                ],
                "能力项": "200字以上、范围",
                "被依赖": false
            },
            {
                "point_id": 3,
                "question": "文章中是否包含至少4个文段中的同音词。",
                "corresponding_part": "文章",
                "rule": "any_keywords4:[\"熠熠\",\"意义\",\"异议\",\"意译\"]",
                "dep": [
                    0
                ],
                "能力项": "中文：同音词",
                "被依赖": false
            },
            {
                "point_id": 4,
                "question": "文章中是否至少用到7个文段中[山部]的汉字",
                "corresponding_part": "文章",
                "rule": "any_keywords7:[\"屿\",\"峰\",\"屹\",\"山\",\"岚\",\"峦\",\"嶂\",\"岁\"]",
                "dep": [
                    0
                ],
                "能力项": "结构词",
                "被依赖": false
            },
            {
                "point_id": 5,
                "question": "关键词\"时光\",\"仿佛\",\"美\"在文章中是否出现不超过1次",
                "corresponding_part": "文章",
                "rule": "non_word_freq1:[\"时光\",\"仿佛\",\"美\"]",
                "dep": [
                    0
                ],
                "能力项": "词频",
                "被依赖": false
            }
        ]
    }
]