[
    {
        "category": "general_multi",
        "question": "Vous êtes rédacteur publicitaire et vous rédigez des textes marketing pour une marque de vin issue d’un domaine familial du sud de la France. Votre employeur vous demande de lui soumettre 11 propositions, chacune comprenant un titre et un corps de texte. Chaque titre doit contenir exactement 13 mots français, tandis que le corps de texte doit contenir au moins 114 mots français. Chaque titre doit commencer par « Ici ». Vous devez utiliser le passé composé pour raconter l’histoire de la marque et partager les expériences des utilisateurs précédents. Veuillez noter que chaque texte doit contenir au moins 5 occurrences de verbes auxiliaires, qui doivent être exclusivement être. Veuillez fournir vos réponses dans le format suivant : 1. [Titre]xxxxxx [Texte]xxxxxx 2. [Titre]xxxxxx [Texte]xxxxxx.",
        "corresponding_parts": {
            "标题": "请你按照python list的格式，清除空行后一一抓取每个[Titre]。注意不要对原文的单词、或字母进行任何处理。",
            "文案": "请你按照python list的格式，清除空行后一一抓取每个[Texte]。注意不要对原文的单词、或字母进行任何处理。"
        },
        "sub_questions": [
            {
                "point_id": 0,
                "question": "是否给出了标题和文案",
                "rule": null,
                "dep": [],
                "被依赖": true
            },
            {
                "point_id": 1,
                "question": "是否给出了11个标题",
                "corresponding_part": "标题",
                "rule": "item_count:[11,11]",
                "dep": [
                    0
                ],
                "能力项": "单元数量合规",
                "被依赖": false
            },
            {
                "point_id": 2,
                "question": "是否给出了11个文案",
                "corresponding_part": "文案",
                "rule": "item_count:[11,11]",
                "dep": [
                    0
                ],
                "能力项": "单元数量合规",
                "被依赖": false
            },
            {
                "point_id": 3,
                "question": "每份标题是否为13个法语单词",
                "corresponding_part": "标题",
                "rule": "french_each_length:[13,13]",
                "dep": [
                    0
                ],
                "能力项": "法语词数、精确",
                "被依赖": false
            },
            {
                "point_id": 4,
                "question": "每个标题都是否以Ici开头",
                "corresponding_part": "标题",
                "rule": "startswith_each:[\"Ici\"]",
                "dep": [
                    0
                ],
                "能力项": "特定格式",
                "被依赖": false
            },
            {
                "point_id": 5,
                "question": "每份文案是否不少于114个法语单词",
                "corresponding_part": "文案",
                "rule": "french_each_length:[114,10000]",
                "dep": [
                    0
                ],
                "能力项": "法语词数、范围",
                "被依赖": false
            },
            {
                "point_id": 6,
                "question": "文案中是否讲述了品牌故事",
                "rule": null,
                "dep": [
                    0
                ],
                "能力项": "主题约束",
                "被依赖": false
            },
            {
                "point_id": 7,
                "question": "文案中是否包含了用户体验",
                "rule": null,
                "dep": [
                    0
                ],
                "能力项": "主题约束",
                "被依赖": false
            },
            {
                "point_id": 8,
                "question": "文案中是否至少使用了5次助动词，且助动词都是être",
                "corresponding_part": "文案",
                "rule": "french_passe_compose5:[être]",
                "dep": [
                    0
                ],
                "能力项": "法语：复合过去时",
                "被依赖": false
            }
        ]
    },
    {
        "category": "general_multi",
        "question": "Vous êtes rédacteur publicitaire et vous rédigez des textes marketing pour une marque de vin issue d’un domaine familial du sud de la France. Votre employeur vous demande de lui soumettre 9 propositions, chacune comprenant un titre et un corps de texte. Chaque titre doit contenir exactement 8 mots français, tandis que le corps de texte doit contenir au moins 113 mots français. Chaque titre doit commencer par « Ici ». Vous devez utiliser le passé composé pour raconter l’histoire de la marque et partager les expériences des utilisateurs précédents. Veuillez noter que chaque texte doit contenir au moins 7 occurrences de verbes auxiliaires, qui doivent être exclusivement être. Veuillez fournir vos réponses dans le format suivant : 1. [Titre]xxxxxx [Texte]xxxxxx 2. [Titre]xxxxxx [Texte]xxxxxx.",
        "corresponding_parts": {
            "标题": "请你按照python list的格式，清除空行后一一抓取每个[Titre]。注意不要对原文的单词、或字母进行任何处理。",
            "文案": "请你按照python list的格式，清除空行后一一抓取每个[Texte]。注意不要对原文的单词、或字母进行任何处理。"
        },
        "sub_questions": [
            {
                "point_id": 0,
                "question": "是否给出了标题和文案",
                "rule": null,
                "dep": [],
                "被依赖": true
            },
            {
                "point_id": 1,
                "question": "是否给出了9个标题",
                "corresponding_part": "标题",
                "rule": "item_count:[9,9]",
                "dep": [
                    0
                ],
                "能力项": "单元数量合规",
                "被依赖": false
            },
            {
                "point_id": 2,
                "question": "是否给出了9个文案",
                "corresponding_part": "文案",
                "rule": "item_count:[9,9]",
                "dep": [
                    0
                ],
                "能力项": "单元数量合规",
                "被依赖": false
            },
            {
                "point_id": 3,
                "question": "每份标题是否为8个法语单词",
                "corresponding_part": "标题",
                "rule": "french_each_length:[8,8]",
                "dep": [
                    0
                ],
                "能力项": "法语词数、精确",
                "被依赖": false
            },
            {
                "point_id": 4,
                "question": "每个标题都是否以Ici开头",
                "corresponding_part": "标题",
                "rule": "startswith_each:[\"Ici\"]",
                "dep": [
                    0
                ],
                "能力项": "特定格式",
                "被依赖": false
            },
            {
                "point_id": 5,
                "question": "每份文案是否不少于113个法语单词",
                "corresponding_part": "文案",
                "rule": "french_each_length:[113,10000]",
                "dep": [
                    0
                ],
                "能力项": "法语词数、范围",
                "被依赖": false
            },
            {
                "point_id": 6,
                "question": "文案中是否讲述了品牌故事",
                "rule": null,
                "dep": [
                    0
                ],
                "能力项": "主题约束",
                "被依赖": false
            },
            {
                "point_id": 7,
                "question": "文案中是否包含了用户体验",
                "rule": null,
                "dep": [
                    0
                ],
                "能力项": "主题约束",
                "被依赖": false
            },
            {
                "point_id": 8,
                "question": "文案中是否至少使用了7次助动词，且助动词都是être",
                "corresponding_part": "文案",
                "rule": "french_passe_compose7:[être]",
                "dep": [
                    0
                ],
                "能力项": "法语：复合过去时",
                "被依赖": false
            }
        ]
    },
    {
        "category": "general_multi",
        "question": "Vous êtes rédacteur publicitaire et vous rédigez des textes marketing pour une marque de vin issue d’un domaine familial du sud de la France. Votre employeur vous demande de lui soumettre 7 propositions, chacune comprenant un titre et un corps de texte. Chaque titre doit contenir exactement 9 mots français, tandis que le corps de texte doit contenir au moins 115 mots français. Chaque titre doit commencer par « Ici ». Vous devez utiliser le passé composé pour raconter l’histoire de la marque et partager les expériences des utilisateurs précédents. Veuillez noter que chaque texte doit contenir au moins 8 occurrences de verbes auxiliaires, qui doivent être exclusivement être. Veuillez fournir vos réponses dans le format suivant : 1. [Titre]xxxxxx [Texte]xxxxxx 2. [Titre]xxxxxx [Texte]xxxxxx.",
        "corresponding_parts": {
            "标题": "请你按照python list的格式，清除空行后一一抓取每个[Titre]。注意不要对原文的单词、或字母进行任何处理。",
            "文案": "请你按照python list的格式，清除空行后一一抓取每个[Texte]。注意不要对原文的单词、或字母进行任何处理。"
        },
        "sub_questions": [
            {
                "point_id": 0,
                "question": "是否给出了标题和文案",
                "rule": null,
                "dep": [],
                "被依赖": true
            },
            {
                "point_id": 1,
                "question": "是否给出了7个标题",
                "corresponding_part": "标题",
                "rule": "item_count:[7,7]",
                "dep": [
                    0
                ],
                "能力项": "单元数量合规",
                "被依赖": false
            },
            {
                "point_id": 2,
                "question": "是否给出了7个文案",
                "corresponding_part": "文案",
                "rule": "item_count:[7,7]",
                "dep": [
                    0
                ],
                "能力项": "单元数量合规",
                "被依赖": false
            },
            {
                "point_id": 3,
                "question": "每份标题是否为9个法语单词",
                "corresponding_part": "标题",
                "rule": "french_each_length:[9,9]",
                "dep": [
                    0
                ],
                "能力项": "法语词数、精确",
                "被依赖": false
            },
            {
                "point_id": 4,
                "question": "每个标题都是否以Ici开头",
                "corresponding_part": "标题",
                "rule": "startswith_each:[\"Ici\"]",
                "dep": [
                    0
                ],
                "能力项": "特定格式",
                "被依赖": false
            },
            {
                "point_id": 5,
                "question": "每份文案是否不少于115个法语单词",
                "corresponding_part": "文案",
                "rule": "french_each_length:[115,10000]",
                "dep": [
                    0
                ],
                "能力项": "法语词数、范围",
                "被依赖": false
            },
            {
                "point_id": 6,
                "question": "文案中是否讲述了品牌故事",
                "rule": null,
                "dep": [
                    0
                ],
                "能力项": "主题约束",
                "被依赖": false
            },
            {
                "point_id": 7,
                "question": "文案中是否包含了用户体验",
                "rule": null,
                "dep": [
                    0
                ],
                "能力项": "主题约束",
                "被依赖": false
            },
            {
                "point_id": 8,
                "question": "文案中是否至少使用了8次助动词，且助动词都是être",
                "corresponding_part": "文案",
                "rule": "french_passe_compose8:[être]",
                "dep": [
                    0
                ],
                "能力项": "法语：复合过去时",
                "被依赖": false
            }
        ]
    },
    {
        "category": "general_multi",
        "question": "Vous êtes rédacteur publicitaire et vous rédigez des textes marketing pour une marque de vin issue d’un domaine familial du sud de la France. Votre employeur vous demande de lui soumettre 4 propositions, chacune comprenant un titre et un corps de texte. Chaque titre doit contenir exactement 12 mots français, tandis que le corps de texte doit contenir au moins 116 mots français. Chaque titre doit commencer par « Ici ». Vous devez utiliser le passé composé pour raconter l’histoire de la marque et partager les expériences des utilisateurs précédents. Veuillez noter que chaque texte doit contenir au moins 10 occurrences de verbes auxiliaires, qui doivent être exclusivement être. Veuillez fournir vos réponses dans le format suivant : 1. [Titre]xxxxxx [Texte]xxxxxx 2. [Titre]xxxxxx [Texte]xxxxxx.",
        "corresponding_parts": {
            "标题": "请你按照python list的格式，清除空行后一一抓取每个[Titre]。注意不要对原文的单词、或字母进行任何处理。",
            "文案": "请你按照python list的格式，清除空行后一一抓取每个[Texte]。注意不要对原文的单词、或字母进行任何处理。"
        },
        "sub_questions": [
            {
                "point_id": 0,
                "question": "是否给出了标题和文案",
                "rule": null,
                "dep": [],
                "被依赖": true
            },
            {
                "point_id": 1,
                "question": "是否给出了4个标题",
                "corresponding_part": "标题",
                "rule": "item_count:[4,4]",
                "dep": [
                    0
                ],
                "能力项": "单元数量合规",
                "被依赖": false
            },
            {
                "point_id": 2,
                "question": "是否给出了4个文案",
                "corresponding_part": "文案",
                "rule": "item_count:[4,4]",
                "dep": [
                    0
                ],
                "能力项": "单元数量合规",
                "被依赖": false
            },
            {
                "point_id": 3,
                "question": "每份标题是否为12个法语单词",
                "corresponding_part": "标题",
                "rule": "french_each_length:[12,12]",
                "dep": [
                    0
                ],
                "能力项": "法语词数、精确",
                "被依赖": false
            },
            {
                "point_id": 4,
                "question": "每个标题都是否以Ici开头",
                "corresponding_part": "标题",
                "rule": "startswith_each:[\"Ici\"]",
                "dep": [
                    0
                ],
                "能力项": "特定格式",
                "被依赖": false
            },
            {
                "point_id": 5,
                "question": "每份文案是否不少于116个法语单词",
                "corresponding_part": "文案",
                "rule": "french_each_length:[116,10000]",
                "dep": [
                    0
                ],
                "能力项": "法语词数、范围",
                "被依赖": false
            },
            {
                "point_id": 6,
                "question": "文案中是否讲述了品牌故事",
                "rule": null,
                "dep": [
                    0
                ],
                "能力项": "主题约束",
                "被依赖": false
            },
            {
                "point_id": 7,
                "question": "文案中是否包含了用户体验",
                "rule": null,
                "dep": [
                    0
                ],
                "能力项": "主题约束",
                "被依赖": false
            },
            {
                "point_id": 8,
                "question": "文案中是否至少使用了10次助动词，且助动词都是être",
                "corresponding_part": "文案",
                "rule": "french_passe_compose10:[être]",
                "dep": [
                    0
                ],
                "能力项": "法语：复合过去时",
                "被依赖": false
            }
        ]
    },
    {
        "category": "general_multi",
        "question": "Vous êtes rédacteur publicitaire et vous rédigez des textes marketing pour une marque de vin issue d’un domaine familial du sud de la France. Votre employeur vous demande de lui soumettre 10 propositions, chacune comprenant un titre et un corps de texte. Chaque titre doit contenir exactement 15 mots français, tandis que le corps de texte doit contenir au moins 117 mots français. Chaque titre doit commencer par « Ici ». Vous devez utiliser le passé composé pour raconter l’histoire de la marque et partager les expériences des utilisateurs précédents. Veuillez noter que chaque texte doit contenir au moins 12 occurrences de verbes auxiliaires, qui doivent être exclusivement être. Veuillez fournir vos réponses dans le format suivant : 1. [Titre]xxxxxx [Texte]xxxxxx 2. [Titre]xxxxxx [Texte]xxxxxx.",
        "corresponding_parts": {
            "标题": "请你按照python list的格式，清除空行后一一抓取每个[Titre]。注意不要对原文的单词、或字母进行任何处理。",
            "文案": "请你按照python list的格式，清除空行后一一抓取每个[Texte]。注意不要对原文的单词、或字母进行任何处理。"
        },
        "sub_questions": [
            {
                "point_id": 0,
                "question": "是否给出了标题和文案",
                "rule": null,
                "dep": [],
                "被依赖": true
            },
            {
                "point_id": 1,
                "question": "是否给出了10个标题",
                "corresponding_part": "标题",
                "rule": "item_count:[10,10]",
                "dep": [
                    0
                ],
                "能力项": "单元数量合规",
                "被依赖": false
            },
            {
                "point_id": 2,
                "question": "是否给出了10个文案",
                "corresponding_part": "文案",
                "rule": "item_count:[10,10]",
                "dep": [
                    0
                ],
                "能力项": "单元数量合规",
                "被依赖": false
            },
            {
                "point_id": 3,
                "question": "每份标题是否为15个法语单词",
                "corresponding_part": "标题",
                "rule": "french_each_length:[15,15]",
                "dep": [
                    0
                ],
                "能力项": "法语词数、精确",
                "被依赖": false
            },
            {
                "point_id": 4,
                "question": "每个标题都是否以Ici开头",
                "corresponding_part": "标题",
                "rule": "startswith_each:[\"Ici\"]",
                "dep": [
                    0
                ],
                "能力项": "特定格式",
                "被依赖": false
            },
            {
                "point_id": 5,
                "question": "每份文案是否不少于117个法语单词",
                "corresponding_part": "文案",
                "rule": "french_each_length:[117,10000]",
                "dep": [
                    0
                ],
                "能力项": "法语词数、范围",
                "被依赖": false
            },
            {
                "point_id": 6,
                "question": "文案中是否讲述了品牌故事",
                "rule": null,
                "dep": [
                    0
                ],
                "能力项": "主题约束",
                "被依赖": false
            },
            {
                "point_id": 7,
                "question": "文案中是否包含了用户体验",
                "rule": null,
                "dep": [
                    0
                ],
                "能力项": "主题约束",
                "被依赖": false
            },
            {
                "point_id": 8,
                "question": "文案中是否至少使用了12次助动词，且助动词都是être",
                "corresponding_part": "文案",
                "rule": "french_passe_compose12:[être]",
                "dep": [
                    0
                ],
                "能力项": "法语：复合过去时",
                "被依赖": false
            }
        ]
    },
    {
        "category": "general_multi",
        "question": "Vous êtes rédacteur publicitaire et vous rédigez des textes marketing pour une marque de vin issue d’un domaine familial du sud de la France. Votre employeur vous demande de lui soumettre 11 propositions, chacune comprenant un titre et un corps de texte. Chaque titre doit contenir exactement 13 mots français, tandis que le corps de texte doit contenir au moins 114 mots français. Chaque titre doit commencer par « Ici ». Vous devez utiliser le passé composé pour raconter l’histoire de la marque et partager les expériences des utilisateurs précédents. Veuillez noter que chaque texte doit contenir au moins 5 occurrences de verbes auxiliaires, qui doivent être exclusivement avoir. Veuillez fournir vos réponses dans le format suivant : 1. [Titre]xxxxxx [Texte]xxxxxx 2. [Titre]xxxxxx [Texte]xxxxxx.",
        "corresponding_parts": {
            "标题": "请你按照python list的格式，清除空行后一一抓取每个[Titre]。注意不要对原文的单词、或字母进行任何处理。",
            "文案": "请你按照python list的格式，清除空行后一一抓取每个[Texte]。注意不要对原文的单词、或字母进行任何处理。"
        },
        "sub_questions": [
            {
                "point_id": 0,
                "question": "是否给出了标题和文案",
                "rule": null,
                "dep": [],
                "被依赖": true
            },
            {
                "point_id": 1,
                "question": "是否给出了11个标题",
                "corresponding_part": "标题",
                "rule": "item_count:[11,11]",
                "dep": [
                    0
                ],
                "能力项": "单元数量合规",
                "被依赖": false
            },
            {
                "point_id": 2,
                "question": "是否给出了11个文案",
                "corresponding_part": "文案",
                "rule": "item_count:[11,11]",
                "dep": [
                    0
                ],
                "能力项": "单元数量合规",
                "被依赖": false
            },
            {
                "point_id": 3,
                "question": "每份标题是否为13个法语单词",
                "corresponding_part": "标题",
                "rule": "french_each_length:[13,13]",
                "dep": [
                    0
                ],
                "能力项": "法语词数、精确",
                "被依赖": false
            },
            {
                "point_id": 4,
                "question": "每个标题都是否以Ici开头",
                "corresponding_part": "标题",
                "rule": "startswith_each:[\"Ici\"]",
                "dep": [
                    0
                ],
                "能力项": "特定格式",
                "被依赖": false
            },
            {
                "point_id": 5,
                "question": "每份文案是否不少于114个法语单词",
                "corresponding_part": "文案",
                "rule": "french_each_length:[114,10000]",
                "dep": [
                    0
                ],
                "能力项": "法语词数、范围",
                "被依赖": false
            },
            {
                "point_id": 6,
                "question": "文案中是否讲述了品牌故事",
                "rule": null,
                "dep": [
                    0
                ],
                "能力项": "主题约束",
                "被依赖": false
            },
            {
                "point_id": 7,
                "question": "文案中是否包含了用户体验",
                "rule": null,
                "dep": [
                    0
                ],
                "能力项": "主题约束",
                "被依赖": false
            },
            {
                "point_id": 8,
                "question": "文案中是否至少使用了5次助动词，且助动词都是avoir",
                "corresponding_part": "文案",
                "rule": "french_passe_compose5:[avoir]",
                "dep": [
                    0
                ],
                "能力项": "法语：复合过去时",
                "被依赖": false
            }
        ]
    },
    {
        "category": "general_multi",
        "question": "Vous êtes rédacteur publicitaire et vous rédigez des textes marketing pour une marque de vin issue d’un domaine familial du sud de la France. Votre employeur vous demande de lui soumettre 9 propositions, chacune comprenant un titre et un corps de texte. Chaque titre doit contenir exactement 8 mots français, tandis que le corps de texte doit contenir au moins 113 mots français. Chaque titre doit commencer par « Ici ». Vous devez utiliser le passé composé pour raconter l’histoire de la marque et partager les expériences des utilisateurs précédents. Veuillez noter que chaque texte doit contenir au moins 7 occurrences de verbes auxiliaires, qui doivent être exclusivement avoir. Veuillez fournir vos réponses dans le format suivant : 1. [Titre]xxxxxx [Texte]xxxxxx 2. [Titre]xxxxxx [Texte]xxxxxx.",
        "corresponding_parts": {
            "标题": "请你按照python list的格式，清除空行后一一抓取每个[Titre]。注意不要对原文的单词、或字母进行任何处理。",
            "文案": "请你按照python list的格式，清除空行后一一抓取每个[Texte]。注意不要对原文的单词、或字母进行任何处理。"
        },
        "sub_questions": [
            {
                "point_id": 0,
                "question": "是否给出了标题和文案",
                "rule": null,
                "dep": [],
                "被依赖": true
            },
            {
                "point_id": 1,
                "question": "是否给出了9个标题",
                "corresponding_part": "标题",
                "rule": "item_count:[9,9]",
                "dep": [
                    0
                ],
                "能力项": "单元数量合规",
                "被依赖": false
            },
            {
                "point_id": 2,
                "question": "是否给出了9个文案",
                "corresponding_part": "文案",
                "rule": "item_count:[9,9]",
                "dep": [
                    0
                ],
                "能力项": "单元数量合规",
                "被依赖": false
            },
            {
                "point_id": 3,
                "question": "每份标题是否为8个法语单词",
                "corresponding_part": "标题",
                "rule": "french_each_length:[8,8]",
                "dep": [
                    0
                ],
                "能力项": "法语词数、精确",
                "被依赖": false
            },
            {
                "point_id": 4,
                "question": "每个标题都是否以Ici开头",
                "corresponding_part": "标题",
                "rule": "startswith_each:[\"Ici\"]",
                "dep": [
                    0
                ],
                "能力项": "特定格式",
                "被依赖": false
            },
            {
                "point_id": 5,
                "question": "每份文案是否不少于113个法语单词",
                "corresponding_part": "文案",
                "rule": "french_each_length:[113,10000]",
                "dep": [
                    0
                ],
                "能力项": "法语词数、范围",
                "被依赖": false
            },
            {
                "point_id": 6,
                "question": "文案中是否讲述了品牌故事",
                "rule": null,
                "dep": [
                    0
                ],
                "能力项": "主题约束",
                "被依赖": false
            },
            {
                "point_id": 7,
                "question": "文案中是否包含了用户体验",
                "rule": null,
                "dep": [
                    0
                ],
                "能力项": "主题约束",
                "被依赖": false
            },
            {
                "point_id": 8,
                "question": "文案中是否至少使用了7次助动词，且助动词都是avoir",
                "corresponding_part": "文案",
                "rule": "french_passe_compose7:[avoir]",
                "dep": [
                    0
                ],
                "能力项": "法语：复合过去时",
                "被依赖": false
            }
        ]
    },
    {
        "category": "general_multi",
        "question": "Vous êtes rédacteur publicitaire et vous rédigez des textes marketing pour une marque de vin issue d’un domaine familial du sud de la France. Votre employeur vous demande de lui soumettre 7 propositions, chacune comprenant un titre et un corps de texte. Chaque titre doit contenir exactement 9 mots français, tandis que le corps de texte doit contenir au moins 115 mots français. Chaque titre doit commencer par « Ici ». Vous devez utiliser le passé composé pour raconter l’histoire de la marque et partager les expériences des utilisateurs précédents. Veuillez noter que chaque texte doit contenir au moins 8 occurrences de verbes auxiliaires, qui doivent être exclusivement avoir. Veuillez fournir vos réponses dans le format suivant : 1. [Titre]xxxxxx [Texte]xxxxxx 2. [Titre]xxxxxx [Texte]xxxxxx.",
        "corresponding_parts": {
            "标题": "请你按照python list的格式，清除空行后一一抓取每个[Titre]。注意不要对原文的单词、或字母进行任何处理。",
            "文案": "请你按照python list的格式，清除空行后一一抓取每个[Texte]。注意不要对原文的单词、或字母进行任何处理。"
        },
        "sub_questions": [
            {
                "point_id": 0,
                "question": "是否给出了标题和文案",
                "rule": null,
                "dep": [],
                "被依赖": true
            },
            {
                "point_id": 1,
                "question": "是否给出了7个标题",
                "corresponding_part": "标题",
                "rule": "item_count:[7,7]",
                "dep": [
                    0
                ],
                "能力项": "单元数量合规",
                "被依赖": false
            },
            {
                "point_id": 2,
                "question": "是否给出了7个文案",
                "corresponding_part": "文案",
                "rule": "item_count:[7,7]",
                "dep": [
                    0
                ],
                "能力项": "单元数量合规",
                "被依赖": false
            },
            {
                "point_id": 3,
                "question": "每份标题是否为9个法语单词",
                "corresponding_part": "标题",
                "rule": "french_each_length:[9,9]",
                "dep": [
                    0
                ],
                "能力项": "法语词数、精确",
                "被依赖": false
            },
            {
                "point_id": 4,
                "question": "每个标题都是否以Ici开头",
                "corresponding_part": "标题",
                "rule": "startswith_each:[\"Ici\"]",
                "dep": [
                    0
                ],
                "能力项": "特定格式",
                "被依赖": false
            },
            {
                "point_id": 5,
                "question": "每份文案是否不少于115个法语单词",
                "corresponding_part": "文案",
                "rule": "french_each_length:[115,10000]",
                "dep": [
                    0
                ],
                "能力项": "法语词数、范围",
                "被依赖": false
            },
            {
                "point_id": 6,
                "question": "文案中是否讲述了品牌故事",
                "rule": null,
                "dep": [
                    0
                ],
                "能力项": "主题约束",
                "被依赖": false
            },
            {
                "point_id": 7,
                "question": "文案中是否包含了用户体验",
                "rule": null,
                "dep": [
                    0
                ],
                "能力项": "主题约束",
                "被依赖": false
            },
            {
                "point_id": 8,
                "question": "文案中是否至少使用了8次助动词，且助动词都是avoir",
                "corresponding_part": "文案",
                "rule": "french_passe_compose8:[avoir]",
                "dep": [
                    0
                ],
                "能力项": "法语：复合过去时",
                "被依赖": false
            }
        ]
    },
    {
        "category": "general_multi",
        "question": "Vous êtes rédacteur publicitaire et vous rédigez des textes marketing pour une marque de vin issue d’un domaine familial du sud de la France. Votre employeur vous demande de lui soumettre 4 propositions, chacune comprenant un titre et un corps de texte. Chaque titre doit contenir exactement 12 mots français, tandis que le corps de texte doit contenir au moins 116 mots français. Chaque titre doit commencer par « Ici ». Vous devez utiliser le passé composé pour raconter l’histoire de la marque et partager les expériences des utilisateurs précédents. Veuillez noter que chaque texte doit contenir au moins 10 occurrences de verbes auxiliaires, qui doivent être exclusivement avoir. Veuillez fournir vos réponses dans le format suivant : 1. [Titre]xxxxxx [Texte]xxxxxx 2. [Titre]xxxxxx [Texte]xxxxxx.",
        "corresponding_parts": {
            "标题": "请你按照python list的格式，清除空行后一一抓取每个[Titre]。注意不要对原文的单词、或字母进行任何处理。",
            "文案": "请你按照python list的格式，清除空行后一一抓取每个[Texte]。注意不要对原文的单词、或字母进行任何处理。"
        },
        "sub_questions": [
            {
                "point_id": 0,
                "question": "是否给出了标题和文案",
                "rule": null,
                "dep": [],
                "被依赖": true
            },
            {
                "point_id": 1,
                "question": "是否给出了4个标题",
                "corresponding_part": "标题",
                "rule": "item_count:[4,4]",
                "dep": [
                    0
                ],
                "能力项": "单元数量合规",
                "被依赖": false
            },
            {
                "point_id": 2,
                "question": "是否给出了4个文案",
                "corresponding_part": "文案",
                "rule": "item_count:[4,4]",
                "dep": [
                    0
                ],
                "能力项": "单元数量合规",
                "被依赖": false
            },
            {
                "point_id": 3,
                "question": "每份标题是否为12个法语单词",
                "corresponding_part": "标题",
                "rule": "french_each_length:[12,12]",
                "dep": [
                    0
                ],
                "能力项": "法语词数、精确",
                "被依赖": false
            },
            {
                "point_id": 4,
                "question": "每个标题都是否以Ici开头",
                "corresponding_part": "标题",
                "rule": "startswith_each:[\"Ici\"]",
                "dep": [
                    0
                ],
                "能力项": "特定格式",
                "被依赖": false
            },
            {
                "point_id": 5,
                "question": "每份文案是否不少于116个法语单词",
                "corresponding_part": "文案",
                "rule": "french_each_length:[116,10000]",
                "dep": [
                    0
                ],
                "能力项": "法语词数、范围",
                "被依赖": false
            },
            {
                "point_id": 6,
                "question": "文案中是否讲述了品牌故事",
                "rule": null,
                "dep": [
                    0
                ],
                "能力项": "主题约束",
                "被依赖": false
            },
            {
                "point_id": 7,
                "question": "文案中是否包含了用户体验",
                "rule": null,
                "dep": [
                    0
                ],
                "能力项": "主题约束",
                "被依赖": false
            },
            {
                "point_id": 8,
                "question": "文案中是否至少使用了10次助动词，且助动词都是avoir",
                "corresponding_part": "文案",
                "rule": "french_passe_compose10:[avoir]",
                "dep": [
                    0
                ],
                "能力项": "法语：复合过去时",
                "被依赖": false
            }
        ]
    },
    {
        "category": "general_multi",
        "question": "Vous êtes rédacteur publicitaire et vous rédigez des textes marketing pour une marque de vin issue d’un domaine familial du sud de la France. Votre employeur vous demande de lui soumettre 10 propositions, chacune comprenant un titre et un corps de texte. Chaque titre doit contenir exactement 15 mots français, tandis que le corps de texte doit contenir au moins 117 mots français. Chaque titre doit commencer par « Ici ». Vous devez utiliser le passé composé pour raconter l’histoire de la marque et partager les expériences des utilisateurs précédents. Veuillez noter que chaque texte doit contenir au moins 12 occurrences de verbes auxiliaires, qui doivent être exclusivement avoir. Veuillez fournir vos réponses dans le format suivant : 1. [Titre]xxxxxx [Texte]xxxxxx 2. [Titre]xxxxxx [Texte]xxxxxx.",
        "corresponding_parts": {
            "标题": "请你按照python list的格式，清除空行后一一抓取每个[Titre]。注意不要对原文的单词、或字母进行任何处理。",
            "文案": "请你按照python list的格式，清除空行后一一抓取每个[Texte]。注意不要对原文的单词、或字母进行任何处理。"
        },
        "sub_questions": [
            {
                "point_id": 0,
                "question": "是否给出了标题和文案",
                "rule": null,
                "dep": [],
                "被依赖": true
            },
            {
                "point_id": 1,
                "question": "是否给出了10个标题",
                "corresponding_part": "标题",
                "rule": "item_count:[10,10]",
                "dep": [
                    0
                ],
                "能力项": "单元数量合规",
                "被依赖": false
            },
            {
                "point_id": 2,
                "question": "是否给出了10个文案",
                "corresponding_part": "文案",
                "rule": "item_count:[10,10]",
                "dep": [
                    0
                ],
                "能力项": "单元数量合规",
                "被依赖": false
            },
            {
                "point_id": 3,
                "question": "每份标题是否为15个法语单词",
                "corresponding_part": "标题",
                "rule": "french_each_length:[15,15]",
                "dep": [
                    0
                ],
                "能力项": "法语词数、精确",
                "被依赖": false
            },
            {
                "point_id": 4,
                "question": "每个标题都是否以Ici开头",
                "corresponding_part": "标题",
                "rule": "startswith_each:[\"Ici\"]",
                "dep": [
                    0
                ],
                "能力项": "特定格式",
                "被依赖": false
            },
            {
                "point_id": 5,
                "question": "每份文案是否不少于117个法语单词",
                "corresponding_part": "文案",
                "rule": "french_each_length:[117,10000]",
                "dep": [
                    0
                ],
                "能力项": "法语词数、范围",
                "被依赖": false
            },
            {
                "point_id": 6,
                "question": "文案中是否讲述了品牌故事",
                "rule": null,
                "dep": [
                    0
                ],
                "能力项": "主题约束",
                "被依赖": false
            },
            {
                "point_id": 7,
                "question": "文案中是否包含了用户体验",
                "rule": null,
                "dep": [
                    0
                ],
                "能力项": "主题约束",
                "被依赖": false
            },
            {
                "point_id": 8,
                "question": "文案中是否至少使用了12次助动词，且助动词都是avoir",
                "corresponding_part": "文案",
                "rule": "french_passe_compose12:[avoir]",
                "dep": [
                    0
                ],
                "能力项": "法语：复合过去时",
                "被依赖": false
            }
        ]
    }
]