[
    {
        "category": "general_multi",
        "question": "ستقيم ابنتنا ياسمين حفل زفافها يوم الجمعة الموافق 10 أكتوبر/تشرين الأول 2025، الساعة الثالثة بعد الظهر، في العنوان التالي: 156 شارع الملكة فاطمة.أحتاج إلى كتابة رسالتي دعوة لصديقَيّ.أما الأولى: فإلى صديق لم أتواصل معه منذ مدة طويلة، وأرغب في أن تكون رسالة طويلة، بحيث يبلغ عدد كلماتها حوالي 45 كلمة عربية.وأما الثانية: فإلى صديق تحدثت معه هذا الأسبوع، وأرغب في كتابة رسالة قصيرة، بحيث يبلغ عدد كلماتها حوالي 25 كلمة عربية (مع هامش زيادة أو نقصان 10%).يجب أن تكون نسبة الكلمات المؤنثة إلى الكلمات المذكرة في كلتا الرسالتين 1 : 2 على التوالي. (يرجى ملاحظة أن هذا الإحصاء لا يشمل الأفعال).الرجاء كتابة نصّي الدعوة بالشكل التالي: ١.الرسالة الطويلة ٢.الرسالة القصيرة.مع تقديم النص فقط.",
        "corresponding_parts": {
            "长邀请信": "请你提取出模型回答中长信件(١. رسالة طويلة)的部分，不要提取短信件(الرسائل القصيرة)。",
            "短邀请信": "请你提取出模型回答中短信件(الرسائل القصيرة)的部分，不要提取长信件(١. رسالة طويلة)。"
        },
        "sub_questions": [
            {
                "point_id": 0,
                "question": "是否给出了长邀请信和短邀请信",
                "rule": null,
                "dep": [],
                "被依赖": true
            },
            {
                "point_id": 1,
                "question": "长邀请信的阿拉伯语单词数是否在45个左右",
                "corresponding_part": "长邀请信",
                "rule": "arabic_each_length:[40.5,49.5]",
                "dep": [
                    0
                ],
                "能力项": "阿语词数、范围",
                "被依赖": false
            },
            {
                "point_id": 2,
                "question": "短邀请信的阿拉伯语单词数是否在25个左右",
                "corresponding_part": "短邀请信",
                "rule": "arabic_each_length:[22.5,27.5]",
                "dep": [
                    0
                ],
                "能力项": "阿语词数、范围",
                "被依赖": false
            },
            {
                "point_id": 3,
                "question": "邀请信是否提到婚礼，并给出了时间地点",
                "rule": null,
                "dep": [
                    0
                ],
                "能力项": "主题约束",
                "被依赖": false
            },
            {
                "point_id": 4,
                "question": "长邀请信中的阴性词和阳性词比例是否恰好为 1: 2",
                "corresponding_part": "长邀请信",
                "rule": "arabic_gender_ratio_total:[1,2]",
                "dep": [
                    0
                ],
                "能力项": "阿语：阴阳性比例",
                "被依赖": false
            },
            {
                "point_id": 5,
                "question": "短邀请信中的阴性词和阳性词比例是否恰好为 1: 2",
                "corresponding_part": "短邀请信",
                "rule": "arabic_gender_ratio_total:[1,2]",
                "dep": [
                    0
                ],
                "能力项": "阿语：阴阳性比例",
                "被依赖": false
            }
        ]
    },
    {
        "category": "general_multi",
        "question": "ستقيم ابنتنا ياسمين حفل زفافها يوم الجمعة الموافق 10 أكتوبر/تشرين الأول 2025، الساعة الثالثة بعد الظهر، في العنوان التالي: 156 شارع الملكة فاطمة.أحتاج إلى كتابة رسالتي دعوة لصديقَيّ.أما الأولى: فإلى صديق لم أتواصل معه منذ مدة طويلة، وأرغب في أن تكون رسالة طويلة، بحيث يبلغ عدد كلماتها حوالي 42 كلمة عربية.وأما الثانية: فإلى صديق تحدثت معه هذا الأسبوع، وأرغب في كتابة رسالة قصيرة، بحيث يبلغ عدد كلماتها حوالي 27 كلمة عربية (مع هامش زيادة أو نقصان 10%).يجب أن تكون نسبة الكلمات المؤنثة إلى الكلمات المذكرة في كلتا الرسالتين 2 : 3 على التوالي. (يرجى ملاحظة أن هذا الإحصاء لا يشمل الأفعال).الرجاء كتابة نصّي الدعوة بالشكل التالي: ١.الرسالة الطويلة ٢.الرسالة القصيرة.مع تقديم النص فقط.",
        "corresponding_parts": {
            "长邀请信": "请你提取出模型回答中长信件(١. رسالة طويلة)的部分，不要提取短信件(الرسائل القصيرة)。",
            "短邀请信": "请你提取出模型回答中短信件(الرسائل القصيرة)的部分，不要提取长信件(١. رسالة طويلة)。"
        },
        "sub_questions": [
            {
                "point_id": 0,
                "question": "是否给出了长邀请信和短邀请信",
                "rule": null,
                "dep": [],
                "被依赖": true
            },
            {
                "point_id": 1,
                "question": "长邀请信的阿拉伯语单词数是否在42个左右",
                "corresponding_part": "长邀请信",
                "rule": "arabic_each_length:[37.8,46.2]",
                "dep": [
                    0
                ],
                "能力项": "阿语词数、范围",
                "被依赖": false
            },
            {
                "point_id": 2,
                "question": "短邀请信的阿拉伯语单词数是否在27个左右",
                "corresponding_part": "短邀请信",
                "rule": "arabic_each_length:[24.3,29.7]",
                "dep": [
                    0
                ],
                "能力项": "阿语词数、范围",
                "被依赖": false
            },
            {
                "point_id": 3,
                "question": "邀请信是否提到婚礼，并给出了时间地点",
                "rule": null,
                "dep": [
                    0
                ],
                "能力项": "主题约束",
                "被依赖": false
            },
            {
                "point_id": 4,
                "question": "长邀请信中的阴性词和阳性词比例是否恰好为 2: 3",
                "corresponding_part": "长邀请信",
                "rule": "arabic_gender_ratio_total:[2,3]",
                "dep": [
                    0
                ],
                "能力项": "阿语：阴阳性比例",
                "被依赖": false
            },
            {
                "point_id": 5,
                "question": "短邀请信中的阴性词和阳性词比例是否恰好为 2: 3",
                "corresponding_part": "短邀请信",
                "rule": "arabic_gender_ratio_total:[2,3]",
                "dep": [
                    0
                ],
                "能力项": "阿语：阴阳性比例",
                "被依赖": false
            }
        ]
    },
    {
        "category": "general_multi",
        "question": "ستقيم ابنتنا ياسمين حفل زفافها يوم الجمعة الموافق 10 أكتوبر/تشرين الأول 2025، الساعة الثالثة بعد الظهر، في العنوان التالي: 156 شارع الملكة فاطمة.أحتاج إلى كتابة رسالتي دعوة لصديقَيّ.أما الأولى: فإلى صديق لم أتواصل معه منذ مدة طويلة، وأرغب في أن تكون رسالة طويلة، بحيث يبلغ عدد كلماتها حوالي 44 كلمة عربية.وأما الثانية: فإلى صديق تحدثت معه هذا الأسبوع، وأرغب في كتابة رسالة قصيرة، بحيث يبلغ عدد كلماتها حوالي 30 كلمة عربية (مع هامش زيادة أو نقصان 10%).يجب أن تكون نسبة الكلمات المؤنثة إلى الكلمات المذكرة في كلتا الرسالتين 1 : 1 على التوالي. (يرجى ملاحظة أن هذا الإحصاء لا يشمل الأفعال).الرجاء كتابة نصّي الدعوة بالشكل التالي: ١.الرسالة الطويلة ٢.الرسالة القصيرة.مع تقديم النص فقط.",
        "corresponding_parts": {
            "长邀请信": "请你提取出模型回答中长信件(١. رسالة طويلة)的部分，不要提取短信件(الرسائل القصيرة)。",
            "短邀请信": "请你提取出模型回答中短信件(الرسائل القصيرة)的部分，不要提取长信件(١. رسالة طويلة)。"
        },
        "sub_questions": [
            {
                "point_id": 0,
                "question": "是否给出了长邀请信和短邀请信",
                "rule": null,
                "dep": [],
                "被依赖": true
            },
            {
                "point_id": 1,
                "question": "长邀请信的阿拉伯语单词数是否在44个左右",
                "corresponding_part": "长邀请信",
                "rule": "arabic_each_length:[39.6,48.4]",
                "dep": [
                    0
                ],
                "能力项": "阿语词数、范围",
                "被依赖": false
            },
            {
                "point_id": 2,
                "question": "短邀请信的阿拉伯语单词数是否在30个左右",
                "corresponding_part": "短邀请信",
                "rule": "arabic_each_length:[27.0,33.0]",
                "dep": [
                    0
                ],
                "能力项": "阿语词数、范围",
                "被依赖": false
            },
            {
                "point_id": 3,
                "question": "邀请信是否提到婚礼，并给出了时间地点",
                "rule": null,
                "dep": [
                    0
                ],
                "能力项": "主题约束",
                "被依赖": false
            },
            {
                "point_id": 4,
                "question": "长邀请信中的阴性词和阳性词比例是否恰好为 1: 1",
                "corresponding_part": "长邀请信",
                "rule": "arabic_gender_ratio_total:[1,1]",
                "dep": [
                    0
                ],
                "能力项": "阿语：阴阳性比例",
                "被依赖": false
            },
            {
                "point_id": 5,
                "question": "短邀请信中的阴性词和阳性词比例是否恰好为 1: 1",
                "corresponding_part": "短邀请信",
                "rule": "arabic_gender_ratio_total:[1,1]",
                "dep": [
                    0
                ],
                "能力项": "阿语：阴阳性比例",
                "被依赖": false
            }
        ]
    },
    {
        "category": "general_multi",
        "question": "ستقيم ابنتنا ياسمين حفل زفافها يوم الجمعة الموافق 10 أكتوبر/تشرين الأول 2025، الساعة الثالثة بعد الظهر، في العنوان التالي: 156 شارع الملكة فاطمة.أحتاج إلى كتابة رسالتي دعوة لصديقَيّ.أما الأولى: فإلى صديق لم أتواصل معه منذ مدة طويلة، وأرغب في أن تكون رسالة طويلة، بحيث يبلغ عدد كلماتها حوالي 48 كلمة عربية.وأما الثانية: فإلى صديق تحدثت معه هذا الأسبوع، وأرغب في كتابة رسالة قصيرة، بحيث يبلغ عدد كلماتها حوالي 29 كلمة عربية (مع هامش زيادة أو نقصان 10%).يجب أن تكون نسبة الكلمات المؤنثة إلى الكلمات المذكرة في كلتا الرسالتين 3 : 2 على التوالي. (يرجى ملاحظة أن هذا الإحصاء لا يشمل الأفعال).الرجاء كتابة نصّي الدعوة بالشكل التالي: ١.الرسالة الطويلة ٢.الرسالة القصيرة.مع تقديم النص فقط.",
        "corresponding_parts": {
            "长邀请信": "请你提取出模型回答中长信件(١. رسالة طويلة)的部分，不要提取短信件(الرسائل القصيرة)。",
            "短邀请信": "请你提取出模型回答中短信件(الرسائل القصيرة)的部分，不要提取长信件(١. رسالة طويلة)。"
        },
        "sub_questions": [
            {
                "point_id": 0,
                "question": "是否给出了长邀请信和短邀请信",
                "rule": null,
                "dep": [],
                "被依赖": true
            },
            {
                "point_id": 1,
                "question": "长邀请信的阿拉伯语单词数是否在48个左右",
                "corresponding_part": "长邀请信",
                "rule": "arabic_each_length:[43.2,52.8]",
                "dep": [
                    0
                ],
                "能力项": "阿语词数、范围",
                "被依赖": false
            },
            {
                "point_id": 2,
                "question": "短邀请信的阿拉伯语单词数是否在29个左右",
                "corresponding_part": "短邀请信",
                "rule": "arabic_each_length:[26.1,31.9]",
                "dep": [
                    0
                ],
                "能力项": "阿语词数、范围",
                "被依赖": false
            },
            {
                "point_id": 3,
                "question": "邀请信是否提到婚礼，并给出了时间地点",
                "rule": null,
                "dep": [
                    0
                ],
                "能力项": "主题约束",
                "被依赖": false
            },
            {
                "point_id": 4,
                "question": "长邀请信中的阴性词和阳性词比例是否恰好为 3: 2",
                "corresponding_part": "长邀请信",
                "rule": "arabic_gender_ratio_total:[3,2]",
                "dep": [
                    0
                ],
                "能力项": "阿语：阴阳性比例",
                "被依赖": false
            },
            {
                "point_id": 5,
                "question": "短邀请信中的阴性词和阳性词比例是否恰好为 3: 2",
                "corresponding_part": "短邀请信",
                "rule": "arabic_gender_ratio_total:[3,2]",
                "dep": [
                    0
                ],
                "能力项": "阿语：阴阳性比例",
                "被依赖": false
            }
        ]
    },
    {
        "category": "general_multi",
        "question": "ستقيم ابنتنا ياسمين حفل زفافها يوم الجمعة الموافق 10 أكتوبر/تشرين الأول 2025، الساعة الثالثة بعد الظهر، في العنوان التالي: 156 شارع الملكة فاطمة.أحتاج إلى كتابة رسالتي دعوة لصديقَيّ.أما الأولى: فإلى صديق لم أتواصل معه منذ مدة طويلة، وأرغب في أن تكون رسالة طويلة، بحيث يبلغ عدد كلماتها حوالي 46 كلمة عربية.وأما الثانية: فإلى صديق تحدثت معه هذا الأسبوع، وأرغب في كتابة رسالة قصيرة، بحيث يبلغ عدد كلماتها حوالي 28 كلمة عربية (مع هامش زيادة أو نقصان 10%).يجب أن تكون نسبة الكلمات المؤنثة إلى الكلمات المذكرة في كلتا الرسالتين 1 : 3 على التوالي. (يرجى ملاحظة أن هذا الإحصاء لا يشمل الأفعال).الرجاء كتابة نصّي الدعوة بالشكل التالي: ١.الرسالة الطويلة ٢.الرسالة القصيرة.مع تقديم النص فقط.",
        "corresponding_parts": {
            "长邀请信": "请你提取出模型回答中长信件(١. رسالة طويلة)的部分，不要提取短信件(الرسائل القصيرة)。",
            "短邀请信": "请你提取出模型回答中短信件(الرسائل القصيرة)的部分，不要提取长信件(١. رسالة طويلة)。"
        },
        "sub_questions": [
            {
                "point_id": 0,
                "question": "是否给出了长邀请信和短邀请信",
                "rule": null,
                "dep": [],
                "被依赖": true
            },
            {
                "point_id": 1,
                "question": "长邀请信的阿拉伯语单词数是否在46个左右",
                "corresponding_part": "长邀请信",
                "rule": "arabic_each_length:[41.4,50.6]",
                "dep": [
                    0
                ],
                "能力项": "阿语词数、范围",
                "被依赖": false
            },
            {
                "point_id": 2,
                "question": "短邀请信的阿拉伯语单词数是否在28个左右",
                "corresponding_part": "短邀请信",
                "rule": "arabic_each_length:[25.2,30.8]",
                "dep": [
                    0
                ],
                "能力项": "阿语词数、范围",
                "被依赖": false
            },
            {
                "point_id": 3,
                "question": "邀请信是否提到婚礼，并给出了时间地点",
                "rule": null,
                "dep": [
                    0
                ],
                "能力项": "主题约束",
                "被依赖": false
            },
            {
                "point_id": 4,
                "question": "长邀请信中的阴性词和阳性词比例是否恰好为 1: 3",
                "corresponding_part": "长邀请信",
                "rule": "arabic_gender_ratio_total:[1,3]",
                "dep": [
                    0
                ],
                "能力项": "阿语：阴阳性比例",
                "被依赖": false
            },
            {
                "point_id": 5,
                "question": "短邀请信中的阴性词和阳性词比例是否恰好为 1: 3",
                "corresponding_part": "短邀请信",
                "rule": "arabic_gender_ratio_total:[1,3]",
                "dep": [
                    0
                ],
                "能力项": "阿语：阴阳性比例",
                "被依赖": false
            }
        ]
    },
    {
        "category": "general_multi",
        "question": "ستقيم ابنتنا ياسمين حفل زفافها يوم الجمعة الموافق 10 أكتوبر/تشرين الأول 2025، الساعة الثالثة بعد الظهر، في العنوان التالي: 156 شارع الملكة فاطمة.أحتاج إلى كتابة رسالتي دعوة لصديقَيّ.أما الأولى: فإلى صديق لم أتواصل معه منذ مدة طويلة، وأرغب في أن تكون رسالة طويلة، بحيث يبلغ عدد كلماتها حوالي 57 كلمة عربية.وأما الثانية: فإلى صديق تحدثت معه هذا الأسبوع، وأرغب في كتابة رسالة قصيرة، بحيث يبلغ عدد كلماتها حوالي 32 كلمة عربية (مع هامش زيادة أو نقصان 10%).يجب أن تكون نسبة الكلمات المؤنثة إلى الكلمات المذكرة في كلتا الرسالتين 2 : 1 على التوالي. (يرجى ملاحظة أن هذا الإحصاء لا يشمل الأفعال).الرجاء كتابة نصّي الدعوة بالشكل التالي: ١.الرسالة الطويلة ٢.الرسالة القصيرة.مع تقديم النص فقط.",
        "corresponding_parts": {
            "长邀请信": "请你提取出模型回答中长信件(١. رسالة طويلة)的部分，不要提取短信件(الرسائل القصيرة)。",
            "短邀请信": "请你提取出模型回答中短信件(الرسائل القصيرة)的部分，不要提取长信件(١. رسالة طويلة)。"
        },
        "sub_questions": [
            {
                "point_id": 0,
                "question": "是否给出了长邀请信和短邀请信",
                "rule": null,
                "dep": [],
                "被依赖": true
            },
            {
                "point_id": 1,
                "question": "长邀请信的阿拉伯语单词数是否在57个左右",
                "corresponding_part": "长邀请信",
                "rule": "arabic_each_length:[51.3,62.7]",
                "dep": [
                    0
                ],
                "能力项": "阿语词数、范围",
                "被依赖": false
            },
            {
                "point_id": 2,
                "question": "短邀请信的阿拉伯语单词数是否在32个左右",
                "corresponding_part": "短邀请信",
                "rule": "arabic_each_length:[28.8,35.2]",
                "dep": [
                    0
                ],
                "能力项": "阿语词数、范围",
                "被依赖": false
            },
            {
                "point_id": 3,
                "question": "邀请信是否提到婚礼，并给出了时间地点",
                "rule": null,
                "dep": [
                    0
                ],
                "能力项": "主题约束",
                "被依赖": false
            },
            {
                "point_id": 4,
                "question": "长邀请信中的阴性词和阳性词比例是否恰好为 2: 1",
                "corresponding_part": "长邀请信",
                "rule": "arabic_gender_ratio_total:[2,1]",
                "dep": [
                    0
                ],
                "能力项": "阿语：阴阳性比例",
                "被依赖": false
            },
            {
                "point_id": 5,
                "question": "短邀请信中的阴性词和阳性词比例是否恰好为 2: 1",
                "corresponding_part": "短邀请信",
                "rule": "arabic_gender_ratio_total:[2,1]",
                "dep": [
                    0
                ],
                "能力项": "阿语：阴阳性比例",
                "被依赖": false
            }
        ]
    },
    {
        "category": "general_multi",
        "question": "ستقيم ابنتنا ياسمين حفل زفافها يوم الجمعة الموافق 10 أكتوبر/تشرين الأول 2025، الساعة الثالثة بعد الظهر، في العنوان التالي: 156 شارع الملكة فاطمة.أحتاج إلى كتابة رسالتي دعوة لصديقَيّ.أما الأولى: فإلى صديق لم أتواصل معه منذ مدة طويلة، وأرغب في أن تكون رسالة طويلة، بحيث يبلغ عدد كلماتها حوالي 56 كلمة عربية.وأما الثانية: فإلى صديق تحدثت معه هذا الأسبوع، وأرغب في كتابة رسالة قصيرة، بحيث يبلغ عدد كلماتها حوالي 33 كلمة عربية (مع هامش زيادة أو نقصان 10%).يجب أن تكون نسبة الكلمات المؤنثة إلى الكلمات المذكرة في كلتا الرسالتين 1 : 2 على التوالي. (يرجى ملاحظة أن هذا الإحصاء لا يشمل الأفعال).الرجاء كتابة نصّي الدعوة بالشكل التالي: ١.الرسالة الطويلة ٢.الرسالة القصيرة.مع تقديم النص فقط.",
        "corresponding_parts": {
            "长邀请信": "请你提取出模型回答中长信件(١. رسالة طويلة)的部分，不要提取短信件(الرسائل القصيرة)。",
            "短邀请信": "请你提取出模型回答中短信件(الرسائل القصيرة)的部分，不要提取长信件(١. رسالة طويلة)。"
        },
        "sub_questions": [
            {
                "point_id": 0,
                "question": "是否给出了长邀请信和短邀请信",
                "rule": null,
                "dep": [],
                "被依赖": true
            },
            {
                "point_id": 1,
                "question": "长邀请信的阿拉伯语单词数是否在56个左右",
                "corresponding_part": "长邀请信",
                "rule": "arabic_each_length:[50.4,61.6]",
                "dep": [
                    0
                ],
                "能力项": "阿语词数、范围",
                "被依赖": false
            },
            {
                "point_id": 2,
                "question": "短邀请信的阿拉伯语单词数是否在33个左右",
                "corresponding_part": "短邀请信",
                "rule": "arabic_each_length:[29.7,36.3]",
                "dep": [
                    0
                ],
                "能力项": "阿语词数、范围",
                "被依赖": false
            },
            {
                "point_id": 3,
                "question": "邀请信是否提到婚礼，并给出了时间地点",
                "rule": null,
                "dep": [
                    0
                ],
                "能力项": "主题约束",
                "被依赖": false
            },
            {
                "point_id": 4,
                "question": "长邀请信中的阴性词和阳性词比例是否恰好为 1: 2",
                "corresponding_part": "长邀请信",
                "rule": "arabic_gender_ratio_total:[1,2]",
                "dep": [
                    0
                ],
                "能力项": "阿语：阴阳性比例",
                "被依赖": false
            },
            {
                "point_id": 5,
                "question": "短邀请信中的阴性词和阳性词比例是否恰好为 1: 2",
                "corresponding_part": "短邀请信",
                "rule": "arabic_gender_ratio_total:[1,2]",
                "dep": [
                    0
                ],
                "能力项": "阿语：阴阳性比例",
                "被依赖": false
            }
        ]
    },
    {
        "category": "general_multi",
        "question": "ستقيم ابنتنا ياسمين حفل زفافها يوم الجمعة الموافق 10 أكتوبر/تشرين الأول 2025، الساعة الثالثة بعد الظهر، في العنوان التالي: 156 شارع الملكة فاطمة.أحتاج إلى كتابة رسالتي دعوة لصديقَيّ.أما الأولى: فإلى صديق لم أتواصل معه منذ مدة طويلة، وأرغب في أن تكون رسالة طويلة، بحيث يبلغ عدد كلماتها حوالي 59 كلمة عربية.وأما الثانية: فإلى صديق تحدثت معه هذا الأسبوع، وأرغب في كتابة رسالة قصيرة، بحيث يبلغ عدد كلماتها حوالي 38 كلمة عربية (مع هامش زيادة أو نقصان 10%).يجب أن تكون نسبة الكلمات المؤنثة إلى الكلمات المذكرة في كلتا الرسالتين 3 : 4 على التوالي. (يرجى ملاحظة أن هذا الإحصاء لا يشمل الأفعال).الرجاء كتابة نصّي الدعوة بالشكل التالي: ١.الرسالة الطويلة ٢.الرسالة القصيرة.مع تقديم النص فقط.",
        "corresponding_parts": {
            "长邀请信": "请你提取出模型回答中长信件(١. رسالة طويلة)的部分，不要提取短信件(الرسائل القصيرة)。",
            "短邀请信": "请你提取出模型回答中短信件(الرسائل القصيرة)的部分，不要提取长信件(١. رسالة طويلة)。"
        },
        "sub_questions": [
            {
                "point_id": 0,
                "question": "是否给出了长邀请信和短邀请信",
                "rule": null,
                "dep": [],
                "被依赖": true
            },
            {
                "point_id": 1,
                "question": "长邀请信的阿拉伯语单词数是否在59个左右",
                "corresponding_part": "长邀请信",
                "rule": "arabic_each_length:[53.1,64.9]",
                "dep": [
                    0
                ],
                "能力项": "阿语词数、范围",
                "被依赖": false
            },
            {
                "point_id": 2,
                "question": "短邀请信的阿拉伯语单词数是否在38个左右",
                "corresponding_part": "短邀请信",
                "rule": "arabic_each_length:[34.2,41.8]",
                "dep": [
                    0
                ],
                "能力项": "阿语词数、范围",
                "被依赖": false
            },
            {
                "point_id": 3,
                "question": "邀请信是否提到婚礼，并给出了时间地点",
                "rule": null,
                "dep": [
                    0
                ],
                "能力项": "主题约束",
                "被依赖": false
            },
            {
                "point_id": 4,
                "question": "长邀请信中的阴性词和阳性词比例是否恰好为 3: 4",
                "corresponding_part": "长邀请信",
                "rule": "arabic_gender_ratio_total:[3,4]",
                "dep": [
                    0
                ],
                "能力项": "阿语：阴阳性比例",
                "被依赖": false
            },
            {
                "point_id": 5,
                "question": "短邀请信中的阴性词和阳性词比例是否恰好为 3: 4",
                "corresponding_part": "短邀请信",
                "rule": "arabic_gender_ratio_total:[3,4]",
                "dep": [
                    0
                ],
                "能力项": "阿语：阴阳性比例",
                "被依赖": false
            }
        ]
    },
    {
        "category": "general_multi",
        "question": "ستقيم ابنتنا ياسمين حفل زفافها يوم الجمعة الموافق 10 أكتوبر/تشرين الأول 2025، الساعة الثالثة بعد الظهر، في العنوان التالي: 156 شارع الملكة فاطمة.أحتاج إلى كتابة رسالتي دعوة لصديقَيّ.أما الأولى: فإلى صديق لم أتواصل معه منذ مدة طويلة، وأرغب في أن تكون رسالة طويلة، بحيث يبلغ عدد كلماتها حوالي 54 كلمة عربية.وأما الثانية: فإلى صديق تحدثت معه هذا الأسبوع، وأرغب في كتابة رسالة قصيرة، بحيث يبلغ عدد كلماتها حوالي 32 كلمة عربية (مع هامش زيادة أو نقصان 10%).يجب أن تكون نسبة الكلمات المؤنثة إلى الكلمات المذكرة في كلتا الرسالتين 2 : 3 على التوالي. (يرجى ملاحظة أن هذا الإحصاء لا يشمل الأفعال).الرجاء كتابة نصّي الدعوة بالشكل التالي: ١.الرسالة الطويلة ٢.الرسالة القصيرة.مع تقديم النص فقط.",
        "corresponding_parts": {
            "长邀请信": "请你提取出模型回答中长信件(١. رسالة طويلة)的部分，不要提取短信件(الرسائل القصيرة)。",
            "短邀请信": "请你提取出模型回答中短信件(الرسائل القصيرة)的部分，不要提取长信件(١. رسالة طويلة)。"
        },
        "sub_questions": [
            {
                "point_id": 0,
                "question": "是否给出了长邀请信和短邀请信",
                "rule": null,
                "dep": [],
                "被依赖": true
            },
            {
                "point_id": 1,
                "question": "长邀请信的阿拉伯语单词数是否在54个左右",
                "corresponding_part": "长邀请信",
                "rule": "arabic_each_length:[48.6,59.4]",
                "dep": [
                    0
                ],
                "能力项": "阿语词数、范围",
                "被依赖": false
            },
            {
                "point_id": 2,
                "question": "短邀请信的阿拉伯语单词数是否在32个左右",
                "corresponding_part": "短邀请信",
                "rule": "arabic_each_length:[28.8,35.2]",
                "dep": [
                    0
                ],
                "能力项": "阿语词数、范围",
                "被依赖": false
            },
            {
                "point_id": 3,
                "question": "邀请信是否提到婚礼，并给出了时间地点",
                "rule": null,
                "dep": [
                    0
                ],
                "能力项": "主题约束",
                "被依赖": false
            },
            {
                "point_id": 4,
                "question": "长邀请信中的阴性词和阳性词比例是否恰好为 2: 3",
                "corresponding_part": "长邀请信",
                "rule": "arabic_gender_ratio_total:[2,3]",
                "dep": [
                    0
                ],
                "能力项": "阿语：阴阳性比例",
                "被依赖": false
            },
            {
                "point_id": 5,
                "question": "短邀请信中的阴性词和阳性词比例是否恰好为 2: 3",
                "corresponding_part": "短邀请信",
                "rule": "arabic_gender_ratio_total:[2,3]",
                "dep": [
                    0
                ],
                "能力项": "阿语：阴阳性比例",
                "被依赖": false
            }
        ]
    },
    {
        "category": "general_multi",
        "question": "ستقيم ابنتنا ياسمين حفل زفافها يوم الجمعة الموافق 10 أكتوبر/تشرين الأول 2025، الساعة الثالثة بعد الظهر، في العنوان التالي: 156 شارع الملكة فاطمة.أحتاج إلى كتابة رسالتي دعوة لصديقَيّ.أما الأولى: فإلى صديق لم أتواصل معه منذ مدة طويلة، وأرغب في أن تكون رسالة طويلة، بحيث يبلغ عدد كلماتها حوالي 53 كلمة عربية.وأما الثانية: فإلى صديق تحدثت معه هذا الأسبوع، وأرغب في كتابة رسالة قصيرة، بحيث يبلغ عدد كلماتها حوالي 31 كلمة عربية (مع هامش زيادة أو نقصان 10%).يجب أن تكون نسبة الكلمات المؤنثة إلى الكلمات المذكرة في كلتا الرسالتين 1 : 1 على التوالي. (يرجى ملاحظة أن هذا الإحصاء لا يشمل الأفعال).الرجاء كتابة نصّي الدعوة بالشكل التالي: ١.الرسالة الطويلة ٢.الرسالة القصيرة.مع تقديم النص فقط.",
        "corresponding_parts": {
            "长邀请信": "请你提取出模型回答中长信件(١. رسالة طويلة)的部分，不要提取短信件(الرسائل القصيرة)。",
            "短邀请信": "请你提取出模型回答中短信件(الرسائل القصيرة)的部分，不要提取长信件(١. رسالة طويلة)。"
        },
        "sub_questions": [
            {
                "point_id": 0,
                "question": "是否给出了长邀请信和短邀请信",
                "rule": null,
                "dep": [],
                "被依赖": true
            },
            {
                "point_id": 1,
                "question": "长邀请信的阿拉伯语单词数是否在53个左右",
                "corresponding_part": "长邀请信",
                "rule": "arabic_each_length:[47.7,58.3]",
                "dep": [
                    0
                ],
                "能力项": "阿语词数、范围",
                "被依赖": false
            },
            {
                "point_id": 2,
                "question": "短邀请信的阿拉伯语单词数是否在31个左右",
                "corresponding_part": "短邀请信",
                "rule": "arabic_each_length:[27.9,34.1]",
                "dep": [
                    0
                ],
                "能力项": "阿语词数、范围",
                "被依赖": false
            },
            {
                "point_id": 3,
                "question": "邀请信是否提到婚礼，并给出了时间地点",
                "rule": null,
                "dep": [
                    0
                ],
                "能力项": "主题约束",
                "被依赖": false
            },
            {
                "point_id": 4,
                "question": "长邀请信中的阴性词和阳性词比例是否恰好为 1: 1",
                "corresponding_part": "长邀请信",
                "rule": "arabic_gender_ratio_total:[1,1]",
                "dep": [
                    0
                ],
                "能力项": "阿语：阴阳性比例",
                "被依赖": false
            },
            {
                "point_id": 5,
                "question": "短邀请信中的阴性词和阳性词比例是否恰好为 1: 1",
                "corresponding_part": "短邀请信",
                "rule": "arabic_gender_ratio_total:[1,1]",
                "dep": [
                    0
                ],
                "能力项": "阿语：阴阳性比例",
                "被依赖": false
            }
        ]
    }
]